<?xml version="1.0" encoding="utf-8"?>
<Report xmlns="http://xml.kishou.go.jp/jmaxml1/" xmlns:jmx="http://xml.kishou.go.jp/jmaxml1/" xmlns:jmx_add="http://xml.kishou.go.jp/jmaxml1/addition1/">
<Control>
<Title>気象警報・注意報</Title>
<DateTime>2009-07-24T08:09:43Z</DateTime>
<Status>通常</Status>
<EditorialOffice>福岡管区気象台</EditorialOffice>
<PublishingOffice>福岡管区気象台</PublishingOffice>
</Control>
<Head xmlns="http://xml.kishou.go.jp/jmaxml1/informationBasis1/">
<Title>福岡県気象警報・注意報</Title>
<ReportDateTime>2009-07-24T17:09:00+09:00</ReportDateTime>
<TargetDateTime>2009-07-24T17:09:00+09:00</TargetDateTime>
<EventID />
<InfoType>発表</InfoType>
<Serial />
<InfoKind>気象警報・注意報</InfoKind>
<InfoKindVersion>1.0_0</InfoKindVersion>
<Headline>
<Text>福岡地方と北九州・遠賀地区では、２４日夜遅くにかけて所により雷を伴った猛烈な雨のおそれがあります。土砂災害や河川の氾濫、低地の浸水などに警戒して下さい。</Text>
<Information type="気象警報・注意報（府県予報区等）">
<Item>
<Kind>
<Name>大雨警報</Name>
<Code>03</Code>
<Condition>土砂災害、浸水害</Condition>
</Kind>
<Kind>
<Name>洪水警報</Name>
<Code>04</Code>
</Kind>
<Kind>
<Name>雷注意報</Name>
<Code>14</Code>
</Kind>
<Kind>
<Name>強風注意報</Name>
<Code>15</Code>
</Kind>
<Kind>
<Name>波浪注意報</Name>
<Code>16</Code>
</Kind>
<Areas codeType="気象情報／府県予報区・細分区域等">
<Area>
<Name>福岡県</Name>
<Code>400000</Code>
</Area>
</Areas>
</Item>
</Information>
<Information type="気象警報・注意報（一次細分区域等）">
<Item>
<Kind>
<Name>大雨警報</Name>
<Code>03</Code>
<Condition>土砂災害、浸水害</Condition>
</Kind>
<Kind>
<Name>洪水警報</Name>
<Code>04</Code>
</Kind>
<Kind>
<Name>雷注意報</Name>
<Code>14</Code>
</Kind>
<Kind>
<Name>強風注意報</Name>
<Code>15</Code>
</Kind>
<Kind>
<Name>波浪注意報</Name>
<Code>16</Code>
</Kind>
<Areas codeType="気象情報／府県予報区・細分区域等">
<Area>
<Name>福岡地方</Name>
<Code>400010</Code>
</Area>
</Areas>
</Item>
<Item>
<Kind>
<Name>大雨警報</Name>
<Code>03</Code>
<Condition>土砂災害、浸水害</Condition>
</Kind>
<Kind>
<Name>洪水警報</Name>
<Code>04</Code>
</Kind>
<Kind>
<Name>雷注意報</Name>
<Code>14</Code>
</Kind>
<Kind>
<Name>強風注意報</Name>
<Code>15</Code>
</Kind>
<Kind>
<Name>波浪注意報</Name>
<Code>16</Code>
</Kind>
<Areas codeType="気象情報／府県予報区・細分区域等">
<Area>
<Name>北九州地方</Name>
<Code>400020</Code>
</Area>
</Areas>
</Item>
<Item>
<Kind>
<Name>雷注意報</Name>
<Code>14</Code>
</Kind>
<Areas codeType="気象情報／府県予報区・細分区域等">
<Area>
<Name>筑豊地方</Name>
<Code>400030</Code>
</Area>
</Areas>
</Item>
<Item>
<Kind>
<Name>雷注意報</Name>
<Code>14</Code>
</Kind>
<Kind>
<Name>強風注意報</Name>
<Code>15</Code>
</Kind>
<Areas codeType="気象情報／府県予報区・細分区域等">
<Area>
<Name>筑後地方</Name>
<Code>400040</Code>
</Area>
</Areas>
</Item>
</Information>
<Information type="気象警報・注意報（市町村等をまとめた地域等）">
<Item>
<Kind>
<Name>大雨警報</Name>
<Code>03</Code>
<Condition>土砂災害、浸水害</Condition>
</Kind>
<Kind>
<Name>洪水警報</Name>
<Code>04</Code>
</Kind>
<Kind>
<Name>雷注意報</Name>
<Code>14</Code>
</Kind>
<Kind>
<Name>強風注意報</Name>
<Code>15</Code>
</Kind>
<Kind>
<Name>波浪注意報</Name>
<Code>16</Code>
</Kind>
<Areas codeType="気象情報／府県予報区・細分区域等">
<Area>
<Name>福岡地方</Name>
<Code>400010</Code>
</Area>
</Areas>
</Item>
<Item>
<Kind>
<Name>大雨警報</Name>
<Code>03</Code>
<Condition>土砂災害、浸水害</Condition>
</Kind>
<Kind>
<Name>洪水警報</Name>
<Code>04</Code>
</Kind>
<Kind>
<Name>雷注意報</Name>
<Code>14</Code>
</Kind>
<Kind>
<Name>強風注意報</Name>
<Code>15</Code>
</Kind>
<Kind>
<Name>波浪注意報</Name>
<Code>16</Code>
</Kind>
<Areas codeType="気象情報／府県予報区・細分区域等">
<Area>
<Name>北九州・遠賀地区</Name>
<Code>400021</Code>
</Area>
</Areas>
</Item>
<Item>
<Kind>
<Name>雷注意報</Name>
<Code>14</Code>
</Kind>
<Kind>
<Name>強風注意報</Name>
<Code>15</Code>
</Kind>
<Areas codeType="気象情報／府県予報区・細分区域等">
<Area>
<Name>京築</Name>
<Code>400022</Code>
</Area>
</Areas>
</Item>
<Item>
<Kind>
<Name>雷注意報</Name>
<Code>14</Code>
</Kind>
<Areas codeType="気象情報／府県予報区・細分区域等">
<Area>
<Name>筑豊地方</Name>
<Code>400030</Code>
</Area>
</Areas>
</Item>
<Item>
<Kind>
<Name>雷注意報</Name>
<Code>14</Code>
</Kind>
<Areas codeType="気象情報／府県予報区・細分区域等">
<Area>
<Name>筑後北部</Name>
<Code>400041</Code>
</Area>
</Areas>
</Item>
<Item>
<Kind>
<Name>雷注意報</Name>
<Code>14</Code>
</Kind>
<Kind>
<Name>強風注意報</Name>
<Code>15</Code>
</Kind>
<Areas codeType="気象情報／府県予報区・細分区域等">
<Area>
<Name>筑後南部</Name>
<Code>400042</Code>
</Area>
</Areas>
</Item>
</Information>
<Information type="気象警報・注意報（市町村等）">
<Item>
<Kind>
<Name>大雨警報</Name>
<Code>03</Code>
<Condition>土砂災害、浸水害</Condition>
</Kind>
<Kind>
<Name>洪水警報</Name>
<Code>04</Code>
</Kind>
<Kind>
<Name>雷注意報</Name>
<Code>14</Code>
</Kind>
<Kind>
<Name>強風注意報</Name>
<Code>15</Code>
</Kind>
<Kind>
<Name>波浪注意報</Name>
<Code>16</Code>
</Kind>
<Areas codeType="気象・地震・火山情報／市町村等">
<Area>
<Name>北九州市</Name>
<Code>4010000</Code>
</Area>
</Areas>
</Item>
<Item>
<Kind>
<Name>大雨警報</Name>
<Code>03</Code>
<Condition>土砂災害、浸水害</Condition>
</Kind>
<Kind>
<Name>洪水警報</Name>
<Code>04</Code>
</Kind>
<Kind>
<Name>雷注意報</Name>
<Code>14</Code>
</Kind>
<Kind>
<Name>強風注意報</Name>
<Code>15</Code>
</Kind>
<Kind>
<Name>波浪注意報</Name>
<Code>16</Code>
</Kind>
<Areas codeType="気象・地震・火山情報／市町村等">
<Area>
<Name>福岡市</Name>
<Code>4013000</Code>
</Area>
</Areas>
</Item>
<Item>
<Kind>
<Name>雷注意報</Name>
<Code>14</Code>
</Kind>
<Kind>
<Name>強風注意報</Name>
<Code>15</Code>
</Kind>
<Areas codeType="気象・地震・火山情報／市町村等">
<Area>
<Name>大牟田市</Name>
<Code>4020200</Code>
</Area>
</Areas>
</Item>
<Item>
<Kind>
<Name>雷注意報</Name>
<Code>14</Code>
</Kind>
<Areas codeType="気象・地震・火山情報／市町村等">
<Area>
<Name>久留米市</Name>
<Code>4020300</Code>
</Area>
</Areas>
</Item>
<Item>
<Kind>
<Name>雷注意報</Name>
<Code>14</Code>
</Kind>
<Areas codeType="気象・地震・火山情報／市町村等">
<Area>
<Name>直方市</Name>
<Code>4020400</Code>
</Area>
</Areas>
</Item>
<Item>
<Kind>
<Name>雷注意報</Name>
<Code>14</Code>
</Kind>
<Areas codeType="気象・地震・火山情報／市町村等">
<Area>
<Name>飯塚市</Name>
<Code>4020500</Code>
</Area>
</Areas>
</Item>
<Item>
<Kind>
<Name>雷注意報</Name>
<Code>14</Code>
</Kind>
<Areas codeType="気象・地震・火山情報／市町村等">
<Area>
<Name>田川市</Name>
<Code>4020600</Code>
</Area>
</Areas>
</Item>
<Item>
<Kind>
<Name>雷注意報</Name>
<Code>14</Code>
</Kind>
<Kind>
<Name>強風注意報</Name>
<Code>15</Code>
</Kind>
<Areas codeType="気象・地震・火山情報／市町村等">
<Area>
<Name>柳川市</Name>
<Code>4020700</Code>
</Area>
</Areas>
</Item>
<Item>
<Kind>
<Name>雷注意報</Name>
<Code>14</Code>
</Kind>
<Areas codeType="気象・地震・火山情報／市町村等">
<Area>
<Name>八女市</Name>
<Code>4021000</Code>
</Area>
</Areas>
</Item>
<Item>
<Kind>
<Name>雷注意報</Name>
<Code>14</Code>
</Kind>
<Areas codeType="気象・地震・火山情報／市町村等">
<Area>
<Name>筑後市</Name>
<Code>4021100</Code>
</Area>
</Areas>
</Item>
<Item>
<Kind>
<Name>雷注意報</Name>
<Code>14</Code>
</Kind>
<Areas codeType="気象・地震・火山情報／市町村等">
<Area>
<Name>大川市</Name>
<Code>4021200</Code>
</Area>
</Areas>
</Item>
<Item>
<Kind>
<Name>雷注意報</Name>
<Code>14</Code>
</Kind>
<Kind>
<Name>強風注意報</Name>
<Code>15</Code>
</Kind>
<Areas codeType="気象・地震・火山情報／市町村等">
<Area>
<Name>行橋市</Name>
<Code>4021300</Code>
</Area>
</Areas>
</Item>
<Item>
<Kind>
<Name>雷注意報</Name>
<Code>14</Code>
</Kind>
<Kind>
<Name>強風注意報</Name>
<Code>15</Code>
</Kind>
<Areas codeType="気象・地震・火山情報／市町村等">
<Area>
<Name>豊前市</Name>
<Code>4021400</Code>
</Area>
</Areas>
</Item>
<Item>
<Kind>
<Name>大雨警報</Name>
<Code>03</Code>
<Condition>土砂災害、浸水害</Condition>
</Kind>
<Kind>
<Name>洪水警報</Name>
<Code>04</Code>
</Kind>
<Kind>
<Name>雷注意報</Name>
<Code>14</Code>
</Kind>
<Areas codeType="気象・地震・火山情報／市町村等">
<Area>
<Name>中間市</Name>
<Code>4021500</Code>
</Area>
</Areas>
</Item>
<Item>
<Kind>
<Name>雷注意報</Name>
<Code>14</Code>
</Kind>
<Areas codeType="気象・地震・火山情報／市町村等">
<Area>
<Name>小郡市</Name>
<Code>4021600</Code>
</Area>
</Areas>
</Item>
<Item>
<Kind>
<Name>大雨警報</Name>
<Code>03</Code>
<Condition>土砂災害、浸水害</Condition>
</Kind>
<Kind>
<Name>洪水警報</Name>
<Code>04</Code>
</Kind>
<Kind>
<Name>雷注意報</Name>
<Code>14</Code>
</Kind>
<Areas codeType="気象・地震・火山情報／市町村等">
<Area>
<Name>筑紫野市</Name>
<Code>4021700</Code>
</Area>
</Areas>
</Item>
<Item>
<Kind>
<Name>大雨警報</Name>
<Code>03</Code>
<Condition>土砂災害、浸水害</Condition>
</Kind>
<Kind>
<Name>洪水警報</Name>
<Code>04</Code>
</Kind>
<Kind>
<Name>雷注意報</Name>
<Code>14</Code>
</Kind>
<Areas codeType="気象・地震・火山情報／市町村等">
<Area>
<Name>春日市</Name>
<Code>4021800</Code>
</Area>
</Areas>
</Item>
<Item>
<Kind>
<Name>大雨警報</Name>
<Code>03</Code>
<Condition>土砂災害、浸水害</Condition>
</Kind>
<Kind>
<Name>洪水警報</Name>
<Code>04</Code>
</Kind>
<Kind>
<Name>雷注意報</Name>
<Code>14</Code>
</Kind>
<Areas codeType="気象・地震・火山情報／市町村等">
<Area>
<Name>大野城市</Name>
<Code>4021900</Code>
</Area>
</Areas>
</Item>
<Item>
<Kind>
<Name>大雨警報</Name>
<Code>03</Code>
<Condition>土砂災害、浸水害</Condition>
</Kind>
<Kind>
<Name>洪水警報</Name>
<Code>04</Code>
</Kind>
<Kind>
<Name>雷注意報</Name>
<Code>14</Code>
</Kind>
<Kind>
<Name>強風注意報</Name>
<Code>15</Code>
</Kind>
<Kind>
<Name>波浪注意報</Name>
<Code>16</Code>
</Kind>
<Areas codeType="気象・地震・火山情報／市町村等">
<Area>
<Name>宗像市</Name>
<Code>4022000</Code>
</Area>
</Areas>
</Item>
<Item>
<Kind>
<Name>大雨警報</Name>
<Code>03</Code>
<Condition>土砂災害、浸水害</Condition>
</Kind>
<Kind>
<Name>洪水警報</Name>
<Code>04</Code>
</Kind>
<Kind>
<Name>雷注意報</Name>
<Code>14</Code>
</Kind>
<Areas codeType="気象・地震・火山情報／市町村等">
<Area>
<Name>太宰府市</Name>
<Code>4022100</Code>
</Area>
</Areas>
</Item>
<Item>
<Kind>
<Name>大雨警報</Name>
<Code>03</Code>
<Condition>土砂災害、浸水害</Condition>
</Kind>
<Kind>
<Name>洪水警報</Name>
<Code>04</Code>
</Kind>
<Kind>
<Name>雷注意報</Name>
<Code>14</Code>
</Kind>
<Kind>
<Name>強風注意報</Name>
<Code>15</Code>
</Kind>
<Kind>
<Name>波浪注意報</Name>
<Code>16</Code>
</Kind>
<Areas codeType="気象・地震・火山情報／市町村等">
<Area>
<Name>古賀市</Name>
<Code>4022300</Code>
</Area>
</Areas>
</Item>
<Item>
<Kind>
<Name>大雨警報</Name>
<Code>03</Code>
<Condition>土砂災害、浸水害</Condition>
</Kind>
<Kind>
<Name>洪水警報</Name>
<Code>04</Code>
</Kind>
<Kind>
<Name>雷注意報</Name>
<Code>14</Code>
</Kind>
<Kind>
<Name>強風注意報</Name>
<Code>15</Code>
</Kind>
<Kind>
<Name>波浪注意報</Name>
<Code>16</Code>
</Kind>
<Areas codeType="気象・地震・火山情報／市町村等">
<Area>
<Name>福津市</Name>
<Code>4022400</Code>
</Area>
</Areas>
</Item>
<Item>
<Kind>
<Name>雷注意報</Name>
<Code>14</Code>
</Kind>
<Areas codeType="気象・地震・火山情報／市町村等">
<Area>
<Name>うきは市</Name>
<Code>4022500</Code>
</Area>
</Areas>
</Item>
<Item>
<Kind>
<Name>雷注意報</Name>
<Code>14</Code>
</Kind>
<Areas codeType="気象・地震・火山情報／市町村等">
<Area>
<Name>宮若市</Name>
<Code>4022600</Code>
</Area>
</Areas>
</Item>
<Item>
<Kind>
<Name>雷注意報</Name>
<Code>14</Code>
</Kind>
<Areas codeType="気象・地震・火山情報／市町村等">
<Area>
<Name>嘉麻市</Name>
<Code>4022700</Code>
</Area>
</Areas>
</Item>
<Item>
<Kind>
<Name>雷注意報</Name>
<Code>14</Code>
</Kind>
<Areas codeType="気象・地震・火山情報／市町村等">
<Area>
<Name>朝倉市</Name>
<Code>4022800</Code>
</Area>
</Areas>
</Item>
<Item>
<Kind>
<Name>雷注意報</Name>
<Code>14</Code>
</Kind>
<Kind>
<Name>強風注意報</Name>
<Code>15</Code>
</Kind>
<Areas codeType="気象・地震・火山情報／市町村等">
<Area>
<Name>みやま市</Name>
<Code>4022900</Code>
</Area>
</Areas>
</Item>
<Item>
<Kind>
<Name>大雨警報</Name>
<Code>03</Code>
<Condition>土砂災害、浸水害</Condition>
</Kind>
<Kind>
<Name>洪水警報</Name>
<Code>04</Code>
</Kind>
<Kind>
<Name>雷注意報</Name>
<Code>14</Code>
</Kind>
<Kind>
<Name>強風注意報</Name>
<Code>15</Code>
</Kind>
<Kind>
<Name>波浪注意報</Name>
<Code>16</Code>
</Kind>
<Areas codeType="気象・地震・火山情報／市町村等">
<Area>
<Name>糸島市</Name>
<Code>4023000</Code>
</Area>
</Areas>
</Item>
<Item>
<Kind>
<Name>大雨警報</Name>
<Code>03</Code>
<Condition>土砂災害、浸水害</Condition>
</Kind>
<Kind>
<Name>洪水警報</Name>
<Code>04</Code>
</Kind>
<Kind>
<Name>雷注意報</Name>
<Code>14</Code>
</Kind>
<Areas codeType="気象・地震・火山情報／市町村等">
<Area>
<Name>那珂川町</Name>
<Code>4030500</Code>
</Area>
</Areas>
</Item>
<Item>
<Kind>
<Name>大雨警報</Name>
<Code>03</Code>
<Condition>土砂災害、浸水害</Condition>
</Kind>
<Kind>
<Name>洪水警報</Name>
<Code>04</Code>
</Kind>
<Kind>
<Name>雷注意報</Name>
<Code>14</Code>
</Kind>
<Areas codeType="気象・地震・火山情報／市町村等">
<Area>
<Name>宇美町</Name>
<Code>4034100</Code>
</Area>
</Areas>
</Item>
<Item>
<Kind>
<Name>大雨警報</Name>
<Code>03</Code>
<Condition>土砂災害、浸水害</Condition>
</Kind>
<Kind>
<Name>洪水警報</Name>
<Code>04</Code>
</Kind>
<Kind>
<Name>雷注意報</Name>
<Code>14</Code>
</Kind>
<Areas codeType="気象・地震・火山情報／市町村等">
<Area>
<Name>篠栗町</Name>
<Code>4034200</Code>
</Area>
</Areas>
</Item>
<Item>
<Kind>
<Name>大雨警報</Name>
<Code>03</Code>
<Condition>土砂災害、浸水害</Condition>
</Kind>
<Kind>
<Name>洪水警報</Name>
<Code>04</Code>
</Kind>
<Kind>
<Name>雷注意報</Name>
<Code>14</Code>
</Kind>
<Areas codeType="気象・地震・火山情報／市町村等">
<Area>
<Name>志免町</Name>
<Code>4034300</Code>
</Area>
</Areas>
</Item>
<Item>
<Kind>
<Name>大雨警報</Name>
<Code>03</Code>
<Condition>土砂災害、浸水害</Condition>
</Kind>
<Kind>
<Name>洪水警報</Name>
<Code>04</Code>
</Kind>
<Kind>
<Name>雷注意報</Name>
<Code>14</Code>
</Kind>
<Areas codeType="気象・地震・火山情報／市町村等">
<Area>
<Name>須恵町</Name>
<Code>4034400</Code>
</Area>
</Areas>
</Item>
<Item>
<Kind>
<Name>大雨警報</Name>
<Code>03</Code>
<Condition>土砂災害、浸水害</Condition>
</Kind>
<Kind>
<Name>洪水警報</Name>
<Code>04</Code>
</Kind>
<Kind>
<Name>雷注意報</Name>
<Code>14</Code>
</Kind>
<Kind>
<Name>強風注意報</Name>
<Code>15</Code>
</Kind>
<Kind>
<Name>波浪注意報</Name>
<Code>16</Code>
</Kind>
<Areas codeType="気象・地震・火山情報／市町村等">
<Area>
<Name>新宮町</Name>
<Code>4034500</Code>
</Area>
</Areas>
</Item>
<Item>
<Kind>
<Name>大雨警報</Name>
<Code>03</Code>
<Condition>土砂災害、浸水害</Condition>
</Kind>
<Kind>
<Name>洪水警報</Name>
<Code>04</Code>
</Kind>
<Kind>
<Name>雷注意報</Name>
<Code>14</Code>
</Kind>
<Areas codeType="気象・地震・火山情報／市町村等">
<Area>
<Name>久山町</Name>
<Code>4034800</Code>
</Area>
</Areas>
</Item>
<Item>
<Kind>
<Name>大雨警報</Name>
<Code>03</Code>
<Condition>土砂災害、浸水害</Condition>
</Kind>
<Kind>
<Name>洪水警報</Name>
<Code>04</Code>
</Kind>
<Kind>
<Name>雷注意報</Name>
<Code>14</Code>
</Kind>
<Areas codeType="気象・地震・火山情報／市町村等">
<Area>
<Name>粕屋町</Name>
<Code>4034900</Code>
</Area>
</Areas>
</Item>
<Item>
<Kind>
<Name>大雨警報</Name>
<Code>03</Code>
<Condition>土砂災害、浸水害</Condition>
</Kind>
<Kind>
<Name>洪水警報</Name>
<Code>04</Code>
</Kind>
<Kind>
<Name>雷注意報</Name>
<Code>14</Code>
</Kind>
<Kind>
<Name>強風注意報</Name>
<Code>15</Code>
</Kind>
<Kind>
<Name>波浪注意報</Name>
<Code>16</Code>
</Kind>
<Areas codeType="気象・地震・火山情報／市町村等">
<Area>
<Name>芦屋町</Name>
<Code>4038100</Code>
</Area>
</Areas>
</Item>
<Item>
<Kind>
<Name>大雨警報</Name>
<Code>03</Code>
<Condition>土砂災害、浸水害</Condition>
</Kind>
<Kind>
<Name>洪水警報</Name>
<Code>04</Code>
</Kind>
<Kind>
<Name>雷注意報</Name>
<Code>14</Code>
</Kind>
<Areas codeType="気象・地震・火山情報／市町村等">
<Area>
<Name>水巻町</Name>
<Code>4038200</Code>
</Area>
</Areas>
</Item>
<Item>
<Kind>
<Name>大雨警報</Name>
<Code>03</Code>
<Condition>土砂災害、浸水害</Condition>
</Kind>
<Kind>
<Name>洪水警報</Name>
<Code>04</Code>
</Kind>
<Kind>
<Name>雷注意報</Name>
<Code>14</Code>
</Kind>
<Kind>
<Name>強風注意報</Name>
<Code>15</Code>
</Kind>
<Kind>
<Name>波浪注意報</Name>
<Code>16</Code>
</Kind>
<Areas codeType="気象・地震・火山情報／市町村等">
<Area>
<Name>岡垣町</Name>
<Code>4038300</Code>
</Area>
</Areas>
</Item>
<Item>
<Kind>
<Name>大雨警報</Name>
<Code>03</Code>
<Condition>土砂災害、浸水害</Condition>
</Kind>
<Kind>
<Name>洪水警報</Name>
<Code>04</Code>
</Kind>
<Kind>
<Name>雷注意報</Name>
<Code>14</Code>
</Kind>
<Areas codeType="気象・地震・火山情報／市町村等">
<Area>
<Name>遠賀町</Name>
<Code>4038400</Code>
</Area>
</Areas>
</Item>
<Item>
<Kind>
<Name>雷注意報</Name>
<Code>14</Code>
</Kind>
<Areas codeType="気象・地震・火山情報／市町村等">
<Area>
<Name>小竹町</Name>
<Code>4040100</Code>
</Area>
</Areas>
</Item>
<Item>
<Kind>
<Name>雷注意報</Name>
<Code>14</Code>
</Kind>
<Areas codeType="気象・地震・火山情報／市町村等">
<Area>
<Name>鞍手町</Name>
<Code>4040200</Code>
</Area>
</Areas>
</Item>
<Item>
<Kind>
<Name>雷注意報</Name>
<Code>14</Code>
</Kind>
<Areas codeType="気象・地震・火山情報／市町村等">
<Area>
<Name>桂川町</Name>
<Code>4042100</Code>
</Area>
</Areas>
</Item>
<Item>
<Kind>
<Name>雷注意報</Name>
<Code>14</Code>
</Kind>
<Areas codeType="気象・地震・火山情報／市町村等">
<Area>
<Name>筑前町</Name>
<Code>4044700</Code>
</Area>
</Areas>
</Item>
<Item>
<Kind>
<Name>雷注意報</Name>
<Code>14</Code>
</Kind>
<Areas codeType="気象・地震・火山情報／市町村等">
<Area>
<Name>東峰村</Name>
<Code>4044800</Code>
</Area>
</Areas>
</Item>
<Item>
<Kind>
<Name>雷注意報</Name>
<Code>14</Code>
</Kind>
<Areas codeType="気象・地震・火山情報／市町村等">
<Area>
<Name>大刀洗町</Name>
<Code>4050300</Code>
</Area>
</Areas>
</Item>
<Item>
<Kind>
<Name>雷注意報</Name>
<Code>14</Code>
</Kind>
<Areas codeType="気象・地震・火山情報／市町村等">
<Area>
<Name>大木町</Name>
<Code>4052200</Code>
</Area>
</Areas>
</Item>
<Item>
<Kind>
<Name>雷注意報</Name>
<Code>14</Code>
</Kind>
<Areas codeType="気象・地震・火山情報／市町村等">
<Area>
<Name>広川町</Name>
<Code>4054400</Code>
</Area>
</Areas>
</Item>
<Item>
<Kind>
<Name>雷注意報</Name>
<Code>14</Code>
</Kind>
<Areas codeType="気象・地震・火山情報／市町村等">
<Area>
<Name>香春町</Name>
<Code>4060100</Code>
</Area>
</Areas>
</Item>
<Item>
<Kind>
<Name>雷注意報</Name>
<Code>14</Code>
</Kind>
<Areas codeType="気象・地震・火山情報／市町村等">
<Area>
<Name>添田町</Name>
<Code>4060200</Code>
</Area>
</Areas>
</Item>
<Item>
<Kind>
<Name>雷注意報</Name>
<Code>14</Code>
</Kind>
<Areas codeType="気象・地震・火山情報／市町村等">
<Area>
<Name>糸田町</Name>
<Code>4060400</Code>
</Area>
</Areas>
</Item>
<Item>
<Kind>
<Name>雷注意報</Name>
<Code>14</Code>
</Kind>
<Areas codeType="気象・地震・火山情報／市町村等">
<Area>
<Name>川崎町</Name>
<Code>4060500</Code>
</Area>
</Areas>
</Item>
<Item>
<Kind>
<Name>雷注意報</Name>
<Code>14</Code>
</Kind>
<Areas codeType="気象・地震・火山情報／市町村等">
<Area>
<Name>大任町</Name>
<Code>4060800</Code>
</Area>
</Areas>
</Item>
<Item>
<Kind>
<Name>雷注意報</Name>
<Code>14</Code>
</Kind>
<Areas codeType="気象・地震・火山情報／市町村等">
<Area>
<Name>赤村</Name>
<Code>4060900</Code>
</Area>
</Areas>
</Item>
<Item>
<Kind>
<Name>雷注意報</Name>
<Code>14</Code>
</Kind>
<Areas codeType="気象・地震・火山情報／市町村等">
<Area>
<Name>福智町</Name>
<Code>4061000</Code>
</Area>
</Areas>
</Item>
<Item>
<Kind>
<Name>雷注意報</Name>
<Code>14</Code>
</Kind>
<Kind>
<Name>強風注意報</Name>
<Code>15</Code>
</Kind>
<Areas codeType="気象・地震・火山情報／市町村等">
<Area>
<Name>苅田町</Name>
<Code>4062100</Code>
</Area>
</Areas>
</Item>
<Item>
<Kind>
<Name>雷注意報</Name>
<Code>14</Code>
</Kind>
<Areas codeType="気象・地震・火山情報／市町村等">
<Area>
<Name>みやこ町</Name>
<Code>4062500</Code>
</Area>
</Areas>
</Item>
<Item>
<Kind>
<Name>雷注意報</Name>
<Code>14</Code>
</Kind>
<Kind>
<Name>強風注意報</Name>
<Code>15</Code>
</Kind>
<Areas codeType="気象・地震・火山情報／市町村等">
<Area>
<Name>吉富町</Name>
<Code>4064200</Code>
</Area>
</Areas>
</Item>
<Item>
<Kind>
<Name>雷注意報</Name>
<Code>14</Code>
</Kind>
<Areas codeType="気象・地震・火山情報／市町村等">
<Area>
<Name>上毛町</Name>
<Code>4064600</Code>
</Area>
</Areas>
</Item>
<Item>
<Kind>
<Name>雷注意報</Name>
<Code>14</Code>
</Kind>
<Kind>
<Name>強風注意報</Name>
<Code>15</Code>
</Kind>
<Areas codeType="気象・地震・火山情報／市町村等">
<Area>
<Name>築上町</Name>
<Code>4064700</Code>
</Area>
</Areas>
</Item>
</Information>
<Information type="気象警報・注意報（警報注意報種別毎）">
<Item>
<Kind>
<Name>大雨警報</Name>
<Code>03</Code>
<Condition>土砂災害、浸水害</Condition>
</Kind>
<Areas codeType="気象情報／府県予報区・細分区域等">
<Area>
<Name>福岡地方</Name>
<Code>400010</Code>
</Area>
<Area>
<Name>北九州・遠賀地区</Name>
<Code>400021</Code>
</Area>
</Areas>
</Item>
<Item>
<Kind>
<Name>洪水警報</Name>
<Code>04</Code>
</Kind>
<Areas codeType="気象情報／府県予報区・細分区域等">
<Area>
<Name>福岡地方</Name>
<Code>400010</Code>
</Area>
<Area>
<Name>北九州・遠賀地区</Name>
<Code>400021</Code>
</Area>
</Areas>
</Item>
<Item>
<Kind>
<Name>雷注意報</Name>
<Code>14</Code>
</Kind>
<Areas codeType="気象情報／府県予報区・細分区域等">
<Area>
<Name>福岡県</Name>
<Code>400000</Code>
</Area>
</Areas>
</Item>
<Item>
<Kind>
<Name>強風注意報</Name>
<Code>15</Code>
</Kind>
<Areas codeType="気象情報／府県予報区・細分区域等">
<Area>
<Name>福岡地方</Name>
<Code>400010</Code>
</Area>
<Area>
<Name>北九州地方</Name>
<Code>400020</Code>
</Area>
<Area>
<Name>筑後南部</Name>
<Code>400042</Code>
</Area>
</Areas>
</Item>
<Item>
<Kind>
<Name>波浪注意報</Name>
<Code>16</Code>
</Kind>
<Areas codeType="気象情報／府県予報区・細分区域等">
<Area>
<Name>福岡地方</Name>
<Code>400010</Code>
</Area>
<Area>
<Name>北九州・遠賀地区</Name>
<Code>400021</Code>
</Area>
</Areas>
</Item>
</Information>
</Headline>
</Head>
<Body xmlns="http://xml.kishou.go.jp/jmaxml1/body/meteorology1/" xmlns:jmx_eb="http://xml.kishou.go.jp/jmaxml1/elementBasis1/">
<Notice>この電文はテストサンプルです。</Notice>
<Warning type="気象警報・注意報（府県予報区等）">
<Item>
<Kind>
<Name>大雨警報</Name>
<Code>03</Code>
<Status>発表</Status>
<Condition>土砂災害、浸水害</Condition>
<Attention>
<Note>土砂災害警戒</Note>
<Note>浸水警戒</Note>
</Attention>
</Kind>
<Kind>
<Name>洪水警報</Name>
<Code>04</Code>
<Status>発表</Status>
<Addition>
<Note>氾濫</Note>
</Addition>
</Kind>
<Kind>
<Name>雷注意報</Name>
<Code>14</Code>
<Status>継続</Status>
<Addition>
<Note>竜巻</Note>
</Addition>
</Kind>
<Kind>
<Name>強風注意報</Name>
<Code>15</Code>
<Status>継続</Status>
</Kind>
<Kind>
<Name>波浪注意報</Name>
<Code>16</Code>
<Status>継続</Status>
</Kind>
<Area>
<Name>福岡県</Name>
<Code>400000</Code>
</Area>
<ChangeStatus>警報・注意報種別に変化有</ChangeStatus>
<FullStatus>一部</FullStatus>
<EditingMark>0</EditingMark>
</Item>
</Warning>
<Warning type="気象警報・注意報（一次細分区域等）">
<Item>
<Kind>
<Name>大雨警報</Name>
<Code>03</Code>
<Status>発表</Status>
<Condition>土砂災害、浸水害</Condition>
<Attention>
<Note>土砂災害警戒</Note>
<Note>浸水警戒</Note>
</Attention>
</Kind>
<Kind>
<Name>洪水警報</Name>
<Code>04</Code>
<Status>発表</Status>
<Addition>
<Note>氾濫</Note>
</Addition>
</Kind>
<Kind>
<Name>雷注意報</Name>
<Code>14</Code>
<Status>継続</Status>
<Addition>
<Note>竜巻</Note>
</Addition>
</Kind>
<Kind>
<Name>強風注意報</Name>
<Code>15</Code>
<Status>継続</Status>
</Kind>
<Kind>
<Name>波浪注意報</Name>
<Code>16</Code>
<Status>継続</Status>
</Kind>
<Area>
<Name>福岡地方</Name>
<Code>400010</Code>
</Area>
<ChangeStatus>警報・注意報種別に変化有</ChangeStatus>
<FullStatus>一部</FullStatus>
<EditingMark>1</EditingMark>
</Item>
<Item>
<Kind>
<Name>大雨警報</Name>
<Code>03</Code>
<Status>発表</Status>
<Condition>土砂災害、浸水害</Condition>
<Attention>
<Note>土砂災害警戒</Note>
<Note>浸水警戒</Note>
</Attention>
</Kind>
<Kind>
<Name>洪水警報</Name>
<Code>04</Code>
<Status>発表</Status>
<Addition>
<Note>氾濫</Note>
</Addition>
</Kind>
<Kind>
<Name>雷注意報</Name>
<Code>14</Code>
<Status>継続</Status>
<Addition>
<Note>竜巻</Note>
</Addition>
</Kind>
<Kind>
<Name>強風注意報</Name>
<Code>15</Code>
<Status>継続</Status>
</Kind>
<Kind>
<Name>波浪注意報</Name>
<Code>16</Code>
<Status>継続</Status>
</Kind>
<Area>
<Name>北九州地方</Name>
<Code>400020</Code>
</Area>
<ChangeStatus>警報・注意報種別に変化有</ChangeStatus>
<FullStatus>一部</FullStatus>
<EditingMark>0</EditingMark>
</Item>
<Item>
<Kind>
<Name>雷注意報</Name>
<Code>14</Code>
<Status>継続</Status>
<Addition>
<Note>竜巻</Note>
</Addition>
</Kind>
<Area>
<Name>筑豊地方</Name>
<Code>400030</Code>
</Area>
<ChangeStatus>変化無</ChangeStatus>
<FullStatus>全域</FullStatus>
<EditingMark>1</EditingMark>
</Item>
<Item>
<Kind>
<Name>雷注意報</Name>
<Code>14</Code>
<Status>継続</Status>
<Addition>
<Note>竜巻</Note>
</Addition>
</Kind>
<Kind>
<Name>強風注意報</Name>
<Code>15</Code>
<Status>継続</Status>
</Kind>
<Area>
<Name>筑後地方</Name>
<Code>400040</Code>
</Area>
<ChangeStatus>変化無</ChangeStatus>
<FullStatus>一部</FullStatus>
<EditingMark>0</EditingMark>
</Item>
</Warning>
<Warning type="気象警報・注意報（市町村等をまとめた地域等）">
<Item>
<Kind>
<Name>大雨警報</Name>
<Code>03</Code>
<Status>発表</Status>
<Condition>土砂災害、浸水害</Condition>
<Attention>
<Note>土砂災害警戒</Note>
<Note>浸水警戒</Note>
</Attention>
</Kind>
<Kind>
<Name>洪水警報</Name>
<Code>04</Code>
<Status>発表</Status>
<Addition>
<Note>氾濫</Note>
</Addition>
</Kind>
<Kind>
<Name>雷注意報</Name>
<Code>14</Code>
<Status>継続</Status>
<Addition>
<Note>竜巻</Note>
</Addition>
</Kind>
<Kind>
<Name>強風注意報</Name>
<Code>15</Code>
<Status>継続</Status>
</Kind>
<Kind>
<Name>波浪注意報</Name>
<Code>16</Code>
<Status>継続</Status>
</Kind>
<Area>
<Name>福岡地方</Name>
<Code>400010</Code>
</Area>
<ChangeStatus>警報・注意報種別に変化有</ChangeStatus>
<FullStatus>一部</FullStatus>
<EditingMark>0</EditingMark>
</Item>
<Item>
<Kind>
<Name>大雨警報</Name>
<Code>03</Code>
<Status>発表</Status>
<Condition>土砂災害、浸水害</Condition>
<Attention>
<Note>土砂災害警戒</Note>
<Note>浸水警戒</Note>
</Attention>
</Kind>
<Kind>
<Name>洪水警報</Name>
<Code>04</Code>
<Status>発表</Status>
<Addition>
<Note>氾濫</Note>
</Addition>
</Kind>
<Kind>
<Name>雷注意報</Name>
<Code>14</Code>
<Status>継続</Status>
<Addition>
<Note>竜巻</Note>
</Addition>
</Kind>
<Kind>
<Name>強風注意報</Name>
<Code>15</Code>
<Status>継続</Status>
</Kind>
<Kind>
<Name>波浪注意報</Name>
<Code>16</Code>
<Status>継続</Status>
</Kind>
<Area>
<Name>北九州・遠賀地区</Name>
<Code>400021</Code>
</Area>
<ChangeStatus>警報・注意報種別に変化有</ChangeStatus>
<FullStatus>一部</FullStatus>
<EditingMark>1</EditingMark>
</Item>
<Item>
<Kind>
<Name>雷注意報</Name>
<Code>14</Code>
<Status>継続</Status>
<Addition>
<Note>竜巻</Note>
</Addition>
</Kind>
<Kind>
<Name>強風注意報</Name>
<Code>15</Code>
<Status>継続</Status>
</Kind>
<Area>
<Name>京築</Name>
<Code>400022</Code>
</Area>
<ChangeStatus>変化無</ChangeStatus>
<FullStatus>一部</FullStatus>
<EditingMark>1</EditingMark>
</Item>
<Item>
<Kind>
<Name>雷注意報</Name>
<Code>14</Code>
<Status>継続</Status>
<Addition>
<Note>竜巻</Note>
</Addition>
</Kind>
<Area>
<Name>筑豊地方</Name>
<Code>400030</Code>
</Area>
<ChangeStatus>変化無</ChangeStatus>
<FullStatus>全域</FullStatus>
<EditingMark>0</EditingMark>
</Item>
<Item>
<Kind>
<Name>雷注意報</Name>
<Code>14</Code>
<Status>継続</Status>
<Addition>
<Note>竜巻</Note>
</Addition>
</Kind>
<Area>
<Name>筑後北部</Name>
<Code>400041</Code>
</Area>
<ChangeStatus>変化無</ChangeStatus>
<FullStatus>全域</FullStatus>
<EditingMark>1</EditingMark>
</Item>
<Item>
<Kind>
<Name>雷注意報</Name>
<Code>14</Code>
<Status>継続</Status>
<Addition>
<Note>竜巻</Note>
</Addition>
</Kind>
<Kind>
<Name>強風注意報</Name>
<Code>15</Code>
<Status>継続</Status>
</Kind>
<Area>
<Name>筑後南部</Name>
<Code>400042</Code>
</Area>
<ChangeStatus>変化無</ChangeStatus>
<FullStatus>一部</FullStatus>
<EditingMark>1</EditingMark>
</Item>
</Warning>
<Warning type="気象警報・注意報（市町村等）">
<Item>
<Kind>
<Name>大雨警報</Name>
<Code>03</Code>
<Status>発表</Status>
<Condition>土砂災害、浸水害</Condition>
<Attention>
<Note>土砂災害警戒</Note>
<Note>浸水警戒</Note>
</Attention>
<Property>
<Type>土砂災害</Type>
<WarningPeriod>
<EndTime>
<Date>２５日</Date>
<Term>昼前</Term>
</EndTime>
</WarningPeriod>
<AdvisoryPeriod>
<EndTime>
<Date>２５日</Date>
<Term>夕方</Term>
</EndTime>
</AdvisoryPeriod>
</Property>
<Property>
<Type>浸水</Type>
<WarningPeriod>
<EndTime>
<Date>２４日</Date>
<Term>夜遅く</Term>
</EndTime>
</WarningPeriod>
<AdvisoryPeriod>
<EndTime>
<Date>２５日</Date>
<Term>朝</Term>
</EndTime>
</AdvisoryPeriod>
<PrecipitationPart>
<Base>
<jmx_eb:Precipitation type="１時間最大雨量" unit="mm" description="８０ミリ">80</jmx_eb:Precipitation>
</Base>
</PrecipitationPart>
</Property>
</Kind>
<Kind>
<Name>洪水警報</Name>
<Code>04</Code>
<Status>発表</Status>
<Addition>
<Note>氾濫</Note>
</Addition>
<Property>
<Type>洪水</Type>
<WarningPeriod>
<EndTime>
<Date>２４日</Date>
<Term>夜遅く</Term>
</EndTime>
</WarningPeriod>
<AdvisoryPeriod>
<EndTime>
<Date>２５日</Date>
<Term>朝</Term>
</EndTime>
</AdvisoryPeriod>
</Property>
</Kind>
<Kind>
<Name>雷注意報</Name>
<Code>14</Code>
<Status>継続</Status>
<Addition>
<Note>竜巻</Note>
</Addition>
<Property>
<Type>雷</Type>
<AdvisoryPeriod>
<EndTime>
<Date>２５日</Date>
<Term>夕方</Term>
</EndTime>
</AdvisoryPeriod>
</Property>
</Kind>
<Kind>
<Name>強風注意報</Name>
<Code>15</Code>
<Status>継続</Status>
<Property>
<Type>風</Type>
<AdvisoryPeriod>
<EndTime>
<Date>２５日</Date>
<Term>夕方</Term>
</EndTime>
</AdvisoryPeriod>
<PeakTime>
<Date>２４日</Date>
<Term>夕方</Term>
</PeakTime>
<WindDirectionPart>
<Base>
<jmx_eb:WindDirection type="風向" unit="８方位漢字" description="南の風">南</jmx_eb:WindDirection>
</Base>
</WindDirectionPart>
<WindSpeedPart>
<Base>
<Local>
<AreaName>響灘</AreaName>
<jmx_eb:WindSpeed type="最大風速" unit="m/s" description="１５メートル">15</jmx_eb:WindSpeed>
</Local>
<Local>
<AreaName>瀬戸内側の海上</AreaName>
<jmx_eb:WindSpeed type="最大風速" unit="m/s" description="１２メートル">12</jmx_eb:WindSpeed>
</Local>
</Base>
</WindSpeedPart>
</Property>
</Kind>
<Kind>
<Name>波浪注意報</Name>
<Code>16</Code>
<Status>継続</Status>
<Property>
<Type>波</Type>
<AdvisoryPeriod>
<EndTime>
<Date>２５日</Date>
<Term>夕方</Term>
</EndTime>
</AdvisoryPeriod>
<WaveHeightPart>
<Base>
<Local>
<AreaName>響灘</AreaName>
<jmx_eb:WaveHeight type="波高" unit="m" description="２．５メートル">2.5</jmx_eb:WaveHeight>
</Local>
</Base>
</WaveHeightPart>
</Property>
</Kind>
<Area>
<Name>北九州市</Name>
<Code>4010000</Code>
</Area>
<ChangeStatus>警報・注意報種別に変化有</ChangeStatus>
</Item>
<Item>
<Kind>
<Name>大雨警報</Name>
<Code>03</Code>
<Status>発表</Status>
<Condition>土砂災害、浸水害</Condition>
<Attention>
<Note>土砂災害警戒</Note>
<Note>浸水警戒</Note>
</Attention>
<Property>
<Type>土砂災害</Type>
<WarningPeriod>
<EndTime>
<Date>２５日</Date>
<Term>昼前</Term>
</EndTime>
</WarningPeriod>
<AdvisoryPeriod>
<EndTime>
<Date>２５日</Date>
<Term>夕方</Term>
</EndTime>
</AdvisoryPeriod>
</Property>
<Property>
<Type>浸水</Type>
<WarningPeriod>
<EndTime>
<Date>２４日</Date>
<Term>夜遅く</Term>
</EndTime>
</WarningPeriod>
<AdvisoryPeriod>
<EndTime>
<Date>２５日</Date>
<Term>朝</Term>
</EndTime>
</AdvisoryPeriod>
<PrecipitationPart>
<Base>
<jmx_eb:Precipitation type="１時間最大雨量" unit="mm" description="８０ミリ">80</jmx_eb:Precipitation>
</Base>
</PrecipitationPart>
</Property>
</Kind>
<Kind>
<Name>洪水警報</Name>
<Code>04</Code>
<Status>発表</Status>
<Addition>
<Note>氾濫</Note>
</Addition>
<Property>
<Type>洪水</Type>
<WarningPeriod>
<EndTime>
<Date>２４日</Date>
<Term>夜遅く</Term>
</EndTime>
</WarningPeriod>
<AdvisoryPeriod>
<EndTime>
<Date>２５日</Date>
<Term>朝</Term>
</EndTime>
</AdvisoryPeriod>
</Property>
</Kind>
<Kind>
<Name>雷注意報</Name>
<Code>14</Code>
<Status>継続</Status>
<Addition>
<Note>竜巻</Note>
</Addition>
<Property>
<Type>雷</Type>
<AdvisoryPeriod>
<EndTime>
<Date>２５日</Date>
<Term>夕方</Term>
</EndTime>
</AdvisoryPeriod>
</Property>
</Kind>
<Kind>
<Name>強風注意報</Name>
<Code>15</Code>
<Status>継続</Status>
<Property>
<Type>風</Type>
<AdvisoryPeriod>
<EndTime>
<Date>２５日</Date>
<Term>夕方</Term>
</EndTime>
</AdvisoryPeriod>
<PeakTime>
<Date>２４日</Date>
<Term>夕方</Term>
</PeakTime>
<WindDirectionPart>
<Base>
<jmx_eb:WindDirection type="風向" unit="８方位漢字" description="南の風">南</jmx_eb:WindDirection>
</Base>
<Becoming>
<jmx_eb:WindDirection type="風向" unit="８方位漢字" description="西の風">西</jmx_eb:WindDirection>
</Becoming>
</WindDirectionPart>
<WindSpeedPart>
<Base>
<Local>
<AreaName>玄界灘</AreaName>
<jmx_eb:WindSpeed type="最大風速" unit="m/s" description="１５メートル">15</jmx_eb:WindSpeed>
</Local>
<Local>
<AreaName>沖ノ島周辺</AreaName>
<jmx_eb:WindSpeed type="最大風速" unit="m/s" description="１５メートル">15</jmx_eb:WindSpeed>
</Local>
</Base>
</WindSpeedPart>
</Property>
</Kind>
<Kind>
<Name>波浪注意報</Name>
<Code>16</Code>
<Status>継続</Status>
<Property>
<Type>波</Type>
<AdvisoryPeriod>
<EndTime>
<Date>２５日</Date>
<Term>夕方</Term>
</EndTime>
</AdvisoryPeriod>
<WaveHeightPart>
<Base>
<Local>
<AreaName>玄界灘</AreaName>
<jmx_eb:WaveHeight type="波高" unit="m" description="２．５メートル">2.5</jmx_eb:WaveHeight>
</Local>
<Local>
<AreaName>沖ノ島周辺</AreaName>
<jmx_eb:WaveHeight type="波高" unit="m" description="２．５メートル">2.5</jmx_eb:WaveHeight>
</Local>
</Base>
</WaveHeightPart>
</Property>
</Kind>
<Area>
<Name>福岡市</Name>
<Code>4013000</Code>
</Area>
<ChangeStatus>警報・注意報種別に変化有</ChangeStatus>
</Item>
<Item>
<Kind>
<Name>雷注意報</Name>
<Code>14</Code>
<Status>継続</Status>
<Addition>
<Note>竜巻</Note>
</Addition>
<Property>
<Type>雷</Type>
<AdvisoryPeriod>
<EndTime>
<Date>２５日</Date>
<Term>夕方</Term>
</EndTime>
</AdvisoryPeriod>
</Property>
</Kind>
<Kind>
<Name>強風注意報</Name>
<Code>15</Code>
<Status>継続</Status>
<Property>
<Type>風</Type>
<AdvisoryPeriod>
<EndTime>
<Date>２４日</Date>
<Term>夜のはじめ頃</Term>
</EndTime>
</AdvisoryPeriod>
<WindDirectionPart>
<Base>
<jmx_eb:WindDirection type="風向" unit="８方位漢字" description="南の風">南</jmx_eb:WindDirection>
</Base>
</WindDirectionPart>
<WindSpeedPart>
<Base>
<Local>
<AreaName>海上</AreaName>
<jmx_eb:WindSpeed type="最大風速" unit="m/s" description="１２メートル">12</jmx_eb:WindSpeed>
</Local>
</Base>
</WindSpeedPart>
</Property>
</Kind>
<Area>
<Name>大牟田市</Name>
<Code>4020200</Code>
</Area>
<ChangeStatus>警報・注意報種別に変化無、量的予想事項等に変化有</ChangeStatus>
</Item>
<Item>
<Kind>
<Name>雷注意報</Name>
<Code>14</Code>
<Status>継続</Status>
<Addition>
<Note>竜巻</Note>
</Addition>
<Property>
<Type>雷</Type>
<AdvisoryPeriod>
<EndTime>
<Date>２５日</Date>
<Term>夕方</Term>
</EndTime>
</AdvisoryPeriod>
</Property>
</Kind>
<Area>
<Name>久留米市</Name>
<Code>4020300</Code>
</Area>
<ChangeStatus>警報・注意報種別に変化無、量的予想事項等に変化有</ChangeStatus>
</Item>
<Item>
<Kind>
<Name>雷注意報</Name>
<Code>14</Code>
<Status>継続</Status>
<Addition>
<Note>竜巻</Note>
</Addition>
<Property>
<Type>雷</Type>
<AdvisoryPeriod>
<EndTime>
<Date>２５日</Date>
<Term>夕方</Term>
</EndTime>
</AdvisoryPeriod>
</Property>
</Kind>
<Area>
<Name>直方市</Name>
<Code>4020400</Code>
</Area>
<ChangeStatus>警報・注意報種別に変化無、量的予想事項等に変化有</ChangeStatus>
</Item>
<Item>
<Kind>
<Name>雷注意報</Name>
<Code>14</Code>
<Status>継続</Status>
<Addition>
<Note>竜巻</Note>
</Addition>
<Property>
<Type>雷</Type>
<AdvisoryPeriod>
<EndTime>
<Date>２５日</Date>
<Term>夕方</Term>
</EndTime>
</AdvisoryPeriod>
</Property>
</Kind>
<Area>
<Name>飯塚市</Name>
<Code>4020500</Code>
</Area>
<ChangeStatus>警報・注意報種別に変化無、量的予想事項等に変化有</ChangeStatus>
</Item>
<Item>
<Kind>
<Name>雷注意報</Name>
<Code>14</Code>
<Status>継続</Status>
<Addition>
<Note>竜巻</Note>
</Addition>
<Property>
<Type>雷</Type>
<AdvisoryPeriod>
<EndTime>
<Date>２５日</Date>
<Term>夕方</Term>
</EndTime>
</AdvisoryPeriod>
</Property>
</Kind>
<Area>
<Name>田川市</Name>
<Code>4020600</Code>
</Area>
<ChangeStatus>警報・注意報種別に変化無、量的予想事項等に変化有</ChangeStatus>
</Item>
<Item>
<Kind>
<Name>雷注意報</Name>
<Code>14</Code>
<Status>継続</Status>
<Addition>
<Note>竜巻</Note>
</Addition>
<Property>
<Type>雷</Type>
<AdvisoryPeriod>
<EndTime>
<Date>２５日</Date>
<Term>夕方</Term>
</EndTime>
</AdvisoryPeriod>
</Property>
</Kind>
<Kind>
<Name>強風注意報</Name>
<Code>15</Code>
<Status>継続</Status>
<Property>
<Type>風</Type>
<AdvisoryPeriod>
<EndTime>
<Date>２４日</Date>
<Term>夜のはじめ頃</Term>
</EndTime>
</AdvisoryPeriod>
<WindDirectionPart>
<Base>
<jmx_eb:WindDirection type="風向" unit="８方位漢字" description="南の風">南</jmx_eb:WindDirection>
</Base>
</WindDirectionPart>
<WindSpeedPart>
<Base>
<Local>
<AreaName>海上</AreaName>
<jmx_eb:WindSpeed type="最大風速" unit="m/s" description="１２メートル">12</jmx_eb:WindSpeed>
</Local>
</Base>
</WindSpeedPart>
</Property>
</Kind>
<Area>
<Name>柳川市</Name>
<Code>4020700</Code>
</Area>
<ChangeStatus>警報・注意報種別に変化無、量的予想事項等に変化有</ChangeStatus>
</Item>
<Item>
<Kind>
<Name>雷注意報</Name>
<Code>14</Code>
<Status>継続</Status>
<Addition>
<Note>竜巻</Note>
</Addition>
<Property>
<Type>雷</Type>
<AdvisoryPeriod>
<EndTime>
<Date>２５日</Date>
<Term>夕方</Term>
</EndTime>
</AdvisoryPeriod>
</Property>
</Kind>
<Area>
<Name>八女市</Name>
<Code>4021000</Code>
</Area>
<ChangeStatus>警報・注意報種別に変化無、量的予想事項等に変化有</ChangeStatus>
</Item>
<Item>
<Kind>
<Name>雷注意報</Name>
<Code>14</Code>
<Status>継続</Status>
<Addition>
<Note>竜巻</Note>
</Addition>
<Property>
<Type>雷</Type>
<AdvisoryPeriod>
<EndTime>
<Date>２５日</Date>
<Term>夕方</Term>
</EndTime>
</AdvisoryPeriod>
</Property>
</Kind>
<Area>
<Name>筑後市</Name>
<Code>4021100</Code>
</Area>
<ChangeStatus>警報・注意報種別に変化無、量的予想事項等に変化有</ChangeStatus>
</Item>
<Item>
<Kind>
<Name>雷注意報</Name>
<Code>14</Code>
<Status>継続</Status>
<Addition>
<Note>竜巻</Note>
</Addition>
<Property>
<Type>雷</Type>
<AdvisoryPeriod>
<EndTime>
<Date>２５日</Date>
<Term>夕方</Term>
</EndTime>
</AdvisoryPeriod>
</Property>
</Kind>
<Area>
<Name>大川市</Name>
<Code>4021200</Code>
</Area>
<ChangeStatus>警報・注意報種別に変化無、量的予想事項等に変化有</ChangeStatus>
</Item>
<Item>
<Kind>
<Name>雷注意報</Name>
<Code>14</Code>
<Status>継続</Status>
<Addition>
<Note>竜巻</Note>
</Addition>
<Property>
<Type>雷</Type>
<AdvisoryPeriod>
<EndTime>
<Date>２５日</Date>
<Term>夕方</Term>
</EndTime>
</AdvisoryPeriod>
</Property>
</Kind>
<Kind>
<Name>強風注意報</Name>
<Code>15</Code>
<Status>継続</Status>
<Property>
<Type>風</Type>
<AdvisoryPeriod>
<EndTime>
<Date>２４日</Date>
<Term>夜のはじめ頃</Term>
</EndTime>
</AdvisoryPeriod>
<WindDirectionPart>
<Base>
<jmx_eb:WindDirection type="風向" unit="８方位漢字" description="南東の風">南東</jmx_eb:WindDirection>
</Base>
</WindDirectionPart>
<WindSpeedPart>
<Base>
<Local>
<AreaName>海上</AreaName>
<jmx_eb:WindSpeed type="最大風速" unit="m/s" description="１２メートル">12</jmx_eb:WindSpeed>
</Local>
</Base>
</WindSpeedPart>
</Property>
</Kind>
<Area>
<Name>行橋市</Name>
<Code>4021300</Code>
</Area>
<ChangeStatus>警報・注意報種別に変化無、量的予想事項等に変化有</ChangeStatus>
</Item>
<Item>
<Kind>
<Name>雷注意報</Name>
<Code>14</Code>
<Status>継続</Status>
<Addition>
<Note>竜巻</Note>
</Addition>
<Property>
<Type>雷</Type>
<AdvisoryPeriod>
<EndTime>
<Date>２５日</Date>
<Term>夕方</Term>
</EndTime>
</AdvisoryPeriod>
</Property>
</Kind>
<Kind>
<Name>強風注意報</Name>
<Code>15</Code>
<Status>継続</Status>
<Property>
<Type>風</Type>
<AdvisoryPeriod>
<EndTime>
<Date>２４日</Date>
<Term>夜のはじめ頃</Term>
</EndTime>
</AdvisoryPeriod>
<WindDirectionPart>
<Base>
<jmx_eb:WindDirection type="風向" unit="８方位漢字" description="南東の風">南東</jmx_eb:WindDirection>
</Base>
</WindDirectionPart>
<WindSpeedPart>
<Base>
<Local>
<AreaName>海上</AreaName>
<jmx_eb:WindSpeed type="最大風速" unit="m/s" description="１２メートル">12</jmx_eb:WindSpeed>
</Local>
</Base>
</WindSpeedPart>
</Property>
</Kind>
<Area>
<Name>豊前市</Name>
<Code>4021400</Code>
</Area>
<ChangeStatus>警報・注意報種別に変化無、量的予想事項等に変化有</ChangeStatus>
</Item>
<Item>
<Kind>
<Name>大雨警報</Name>
<Code>03</Code>
<Status>発表</Status>
<Condition>土砂災害、浸水害</Condition>
<Attention>
<Note>土砂災害警戒</Note>
<Note>浸水警戒</Note>
</Attention>
<Property>
<Type>土砂災害</Type>
<WarningPeriod>
<EndTime>
<Date>２５日</Date>
<Term>昼前</Term>
</EndTime>
</WarningPeriod>
<AdvisoryPeriod>
<EndTime>
<Date>２５日</Date>
<Term>夕方</Term>
</EndTime>
</AdvisoryPeriod>
</Property>
<Property>
<Type>浸水</Type>
<WarningPeriod>
<EndTime>
<Date>２４日</Date>
<Term>夜遅く</Term>
</EndTime>
</WarningPeriod>
<AdvisoryPeriod>
<EndTime>
<Date>２５日</Date>
<Term>朝</Term>
</EndTime>
</AdvisoryPeriod>
<PrecipitationPart>
<Base>
<jmx_eb:Precipitation type="１時間最大雨量" unit="mm" description="８０ミリ">80</jmx_eb:Precipitation>
</Base>
</PrecipitationPart>
</Property>
</Kind>
<Kind>
<Name>洪水警報</Name>
<Code>04</Code>
<Status>発表</Status>
<Addition>
<Note>氾濫</Note>
</Addition>
<Property>
<Type>洪水</Type>
<WarningPeriod>
<EndTime>
<Date>２４日</Date>
<Term>夜遅く</Term>
</EndTime>
</WarningPeriod>
<AdvisoryPeriod>
<EndTime>
<Date>２５日</Date>
<Term>朝</Term>
</EndTime>
</AdvisoryPeriod>
</Property>
</Kind>
<Kind>
<Name>雷注意報</Name>
<Code>14</Code>
<Status>継続</Status>
<Addition>
<Note>竜巻</Note>
</Addition>
<Property>
<Type>雷</Type>
<AdvisoryPeriod>
<EndTime>
<Date>２５日</Date>
<Term>夕方</Term>
</EndTime>
</AdvisoryPeriod>
</Property>
</Kind>
<Area>
<Name>中間市</Name>
<Code>4021500</Code>
</Area>
<ChangeStatus>警報・注意報種別に変化有</ChangeStatus>
</Item>
<Item>
<Kind>
<Name>雷注意報</Name>
<Code>14</Code>
<Status>継続</Status>
<Addition>
<Note>竜巻</Note>
</Addition>
<Property>
<Type>雷</Type>
<AdvisoryPeriod>
<EndTime>
<Date>２５日</Date>
<Term>夕方</Term>
</EndTime>
</AdvisoryPeriod>
</Property>
</Kind>
<Area>
<Name>小郡市</Name>
<Code>4021600</Code>
</Area>
<ChangeStatus>警報・注意報種別に変化無、量的予想事項等に変化有</ChangeStatus>
</Item>
<Item>
<Kind>
<Name>大雨警報</Name>
<Code>03</Code>
<Status>発表</Status>
<Condition>土砂災害、浸水害</Condition>
<Attention>
<Note>土砂災害警戒</Note>
<Note>浸水警戒</Note>
</Attention>
<Property>
<Type>土砂災害</Type>
<WarningPeriod>
<EndTime>
<Date>２５日</Date>
<Term>昼前</Term>
</EndTime>
</WarningPeriod>
<AdvisoryPeriod>
<EndTime>
<Date>２５日</Date>
<Term>夕方</Term>
</EndTime>
</AdvisoryPeriod>
</Property>
<Property>
<Type>浸水</Type>
<WarningPeriod>
<EndTime>
<Date>２４日</Date>
<Term>夜遅く</Term>
</EndTime>
</WarningPeriod>
<AdvisoryPeriod>
<EndTime>
<Date>２５日</Date>
<Term>朝</Term>
</EndTime>
</AdvisoryPeriod>
<PrecipitationPart>
<Base>
<jmx_eb:Precipitation type="１時間最大雨量" unit="mm" description="８０ミリ">80</jmx_eb:Precipitation>
</Base>
</PrecipitationPart>
</Property>
</Kind>
<Kind>
<Name>洪水警報</Name>
<Code>04</Code>
<Status>発表</Status>
<Addition>
<Note>氾濫</Note>
</Addition>
<Property>
<Type>洪水</Type>
<WarningPeriod>
<EndTime>
<Date>２４日</Date>
<Term>夜遅く</Term>
</EndTime>
</WarningPeriod>
<AdvisoryPeriod>
<EndTime>
<Date>２５日</Date>
<Term>朝</Term>
</EndTime>
</AdvisoryPeriod>
</Property>
</Kind>
<Kind>
<Name>雷注意報</Name>
<Code>14</Code>
<Status>継続</Status>
<Addition>
<Note>竜巻</Note>
</Addition>
<Property>
<Type>雷</Type>
<AdvisoryPeriod>
<EndTime>
<Date>２５日</Date>
<Term>夕方</Term>
</EndTime>
</AdvisoryPeriod>
</Property>
</Kind>
<Area>
<Name>筑紫野市</Name>
<Code>4021700</Code>
</Area>
<ChangeStatus>警報・注意報種別に変化有</ChangeStatus>
</Item>
<Item>
<Kind>
<Name>大雨警報</Name>
<Code>03</Code>
<Status>発表</Status>
<Condition>土砂災害、浸水害</Condition>
<Attention>
<Note>土砂災害警戒</Note>
<Note>浸水警戒</Note>
</Attention>
<Property>
<Type>土砂災害</Type>
<WarningPeriod>
<EndTime>
<Date>２５日</Date>
<Term>昼前</Term>
</EndTime>
</WarningPeriod>
<AdvisoryPeriod>
<EndTime>
<Date>２５日</Date>
<Term>夕方</Term>
</EndTime>
</AdvisoryPeriod>
</Property>
<Property>
<Type>浸水</Type>
<WarningPeriod>
<EndTime>
<Date>２４日</Date>
<Term>夜遅く</Term>
</EndTime>
</WarningPeriod>
<AdvisoryPeriod>
<EndTime>
<Date>２５日</Date>
<Term>朝</Term>
</EndTime>
</AdvisoryPeriod>
<PrecipitationPart>
<Base>
<jmx_eb:Precipitation type="１時間最大雨量" unit="mm" description="８０ミリ">80</jmx_eb:Precipitation>
</Base>
</PrecipitationPart>
</Property>
</Kind>
<Kind>
<Name>洪水警報</Name>
<Code>04</Code>
<Status>発表</Status>
<Addition>
<Note>氾濫</Note>
</Addition>
<Property>
<Type>洪水</Type>
<WarningPeriod>
<EndTime>
<Date>２４日</Date>
<Term>夜遅く</Term>
</EndTime>
</WarningPeriod>
<AdvisoryPeriod>
<EndTime>
<Date>２５日</Date>
<Term>朝</Term>
</EndTime>
</AdvisoryPeriod>
</Property>
</Kind>
<Kind>
<Name>雷注意報</Name>
<Code>14</Code>
<Status>継続</Status>
<Addition>
<Note>竜巻</Note>
</Addition>
<Property>
<Type>雷</Type>
<AdvisoryPeriod>
<EndTime>
<Date>２５日</Date>
<Term>夕方</Term>
</EndTime>
</AdvisoryPeriod>
</Property>
</Kind>
<Area>
<Name>春日市</Name>
<Code>4021800</Code>
</Area>
<ChangeStatus>警報・注意報種別に変化有</ChangeStatus>
</Item>
<Item>
<Kind>
<Name>大雨警報</Name>
<Code>03</Code>
<Status>発表</Status>
<Condition>土砂災害、浸水害</Condition>
<Attention>
<Note>土砂災害警戒</Note>
<Note>浸水警戒</Note>
</Attention>
<Property>
<Type>土砂災害</Type>
<WarningPeriod>
<EndTime>
<Date>２５日</Date>
<Term>昼前</Term>
</EndTime>
</WarningPeriod>
<AdvisoryPeriod>
<EndTime>
<Date>２５日</Date>
<Term>夕方</Term>
</EndTime>
</AdvisoryPeriod>
</Property>
<Property>
<Type>浸水</Type>
<WarningPeriod>
<EndTime>
<Date>２４日</Date>
<Term>夜遅く</Term>
</EndTime>
</WarningPeriod>
<AdvisoryPeriod>
<EndTime>
<Date>２５日</Date>
<Term>朝</Term>
</EndTime>
</AdvisoryPeriod>
<PrecipitationPart>
<Base>
<jmx_eb:Precipitation type="１時間最大雨量" unit="mm" description="８０ミリ">80</jmx_eb:Precipitation>
</Base>
</PrecipitationPart>
</Property>
</Kind>
<Kind>
<Name>洪水警報</Name>
<Code>04</Code>
<Status>発表</Status>
<Addition>
<Note>氾濫</Note>
</Addition>
<Property>
<Type>洪水</Type>
<WarningPeriod>
<EndTime>
<Date>２４日</Date>
<Term>夜遅く</Term>
</EndTime>
</WarningPeriod>
<AdvisoryPeriod>
<EndTime>
<Date>２５日</Date>
<Term>朝</Term>
</EndTime>
</AdvisoryPeriod>
</Property>
</Kind>
<Kind>
<Name>雷注意報</Name>
<Code>14</Code>
<Status>継続</Status>
<Addition>
<Note>竜巻</Note>
</Addition>
<Property>
<Type>雷</Type>
<AdvisoryPeriod>
<EndTime>
<Date>２５日</Date>
<Term>夕方</Term>
</EndTime>
</AdvisoryPeriod>
</Property>
</Kind>
<Area>
<Name>大野城市</Name>
<Code>4021900</Code>
</Area>
<ChangeStatus>警報・注意報種別に変化有</ChangeStatus>
</Item>
<Item>
<Kind>
<Name>大雨警報</Name>
<Code>03</Code>
<Status>発表</Status>
<Condition>土砂災害、浸水害</Condition>
<Attention>
<Note>土砂災害警戒</Note>
<Note>浸水警戒</Note>
</Attention>
<Property>
<Type>土砂災害</Type>
<WarningPeriod>
<EndTime>
<Date>２５日</Date>
<Term>昼前</Term>
</EndTime>
</WarningPeriod>
<AdvisoryPeriod>
<EndTime>
<Date>２５日</Date>
<Term>夕方</Term>
</EndTime>
</AdvisoryPeriod>
</Property>
<Property>
<Type>浸水</Type>
<WarningPeriod>
<EndTime>
<Date>２４日</Date>
<Term>夜遅く</Term>
</EndTime>
</WarningPeriod>
<AdvisoryPeriod>
<EndTime>
<Date>２５日</Date>
<Term>朝</Term>
</EndTime>
</AdvisoryPeriod>
<PrecipitationPart>
<Base>
<jmx_eb:Precipitation type="１時間最大雨量" unit="mm" description="８０ミリ">80</jmx_eb:Precipitation>
</Base>
</PrecipitationPart>
</Property>
</Kind>
<Kind>
<Name>洪水警報</Name>
<Code>04</Code>
<Status>発表</Status>
<Addition>
<Note>氾濫</Note>
</Addition>
<Property>
<Type>洪水</Type>
<WarningPeriod>
<EndTime>
<Date>２４日</Date>
<Term>夜遅く</Term>
</EndTime>
</WarningPeriod>
<AdvisoryPeriod>
<EndTime>
<Date>２５日</Date>
<Term>朝</Term>
</EndTime>
</AdvisoryPeriod>
</Property>
</Kind>
<Kind>
<Name>雷注意報</Name>
<Code>14</Code>
<Status>継続</Status>
<Addition>
<Note>竜巻</Note>
</Addition>
<Property>
<Type>雷</Type>
<AdvisoryPeriod>
<EndTime>
<Date>２５日</Date>
<Term>夕方</Term>
</EndTime>
</AdvisoryPeriod>
</Property>
</Kind>
<Kind>
<Name>強風注意報</Name>
<Code>15</Code>
<Status>継続</Status>
<Property>
<Type>風</Type>
<AdvisoryPeriod>
<EndTime>
<Date>２５日</Date>
<Term>夕方</Term>
</EndTime>
</AdvisoryPeriod>
<PeakTime>
<Date>２４日</Date>
<Term>夕方</Term>
</PeakTime>
<WindDirectionPart>
<Base>
<jmx_eb:WindDirection type="風向" unit="８方位漢字" description="南の風">南</jmx_eb:WindDirection>
</Base>
<Becoming>
<jmx_eb:WindDirection type="風向" unit="８方位漢字" description="西の風">西</jmx_eb:WindDirection>
</Becoming>
</WindDirectionPart>
<WindSpeedPart>
<Base>
<Local>
<AreaName>玄界灘</AreaName>
<jmx_eb:WindSpeed type="最大風速" unit="m/s" description="１５メートル">15</jmx_eb:WindSpeed>
</Local>
<Local>
<AreaName>沖ノ島周辺</AreaName>
<jmx_eb:WindSpeed type="最大風速" unit="m/s" description="１５メートル">15</jmx_eb:WindSpeed>
</Local>
</Base>
</WindSpeedPart>
</Property>
</Kind>
<Kind>
<Name>波浪注意報</Name>
<Code>16</Code>
<Status>継続</Status>
<Property>
<Type>波</Type>
<AdvisoryPeriod>
<EndTime>
<Date>２５日</Date>
<Term>夕方</Term>
</EndTime>
</AdvisoryPeriod>
<WaveHeightPart>
<Base>
<Local>
<AreaName>玄界灘</AreaName>
<jmx_eb:WaveHeight type="波高" unit="m" description="２．５メートル">2.5</jmx_eb:WaveHeight>
</Local>
<Local>
<AreaName>沖ノ島周辺</AreaName>
<jmx_eb:WaveHeight type="波高" unit="m" description="２．５メートル">2.5</jmx_eb:WaveHeight>
</Local>
</Base>
</WaveHeightPart>
</Property>
</Kind>
<Area>
<Name>宗像市</Name>
<Code>4022000</Code>
</Area>
<ChangeStatus>警報・注意報種別に変化有</ChangeStatus>
</Item>
<Item>
<Kind>
<Name>大雨警報</Name>
<Code>03</Code>
<Status>発表</Status>
<Condition>土砂災害、浸水害</Condition>
<Attention>
<Note>土砂災害警戒</Note>
<Note>浸水警戒</Note>
</Attention>
<Property>
<Type>土砂災害</Type>
<WarningPeriod>
<EndTime>
<Date>２５日</Date>
<Term>昼前</Term>
</EndTime>
</WarningPeriod>
<AdvisoryPeriod>
<EndTime>
<Date>２５日</Date>
<Term>夕方</Term>
</EndTime>
</AdvisoryPeriod>
</Property>
<Property>
<Type>浸水</Type>
<WarningPeriod>
<EndTime>
<Date>２４日</Date>
<Term>夜遅く</Term>
</EndTime>
</WarningPeriod>
<AdvisoryPeriod>
<EndTime>
<Date>２５日</Date>
<Term>朝</Term>
</EndTime>
</AdvisoryPeriod>
<PrecipitationPart>
<Base>
<jmx_eb:Precipitation type="１時間最大雨量" unit="mm" description="８０ミリ">80</jmx_eb:Precipitation>
</Base>
</PrecipitationPart>
</Property>
</Kind>
<Kind>
<Name>洪水警報</Name>
<Code>04</Code>
<Status>発表</Status>
<Addition>
<Note>氾濫</Note>
</Addition>
<Property>
<Type>洪水</Type>
<WarningPeriod>
<EndTime>
<Date>２４日</Date>
<Term>夜遅く</Term>
</EndTime>
</WarningPeriod>
<AdvisoryPeriod>
<EndTime>
<Date>２５日</Date>
<Term>朝</Term>
</EndTime>
</AdvisoryPeriod>
</Property>
</Kind>
<Kind>
<Name>雷注意報</Name>
<Code>14</Code>
<Status>継続</Status>
<Addition>
<Note>竜巻</Note>
</Addition>
<Property>
<Type>雷</Type>
<AdvisoryPeriod>
<EndTime>
<Date>２５日</Date>
<Term>夕方</Term>
</EndTime>
</AdvisoryPeriod>
</Property>
</Kind>
<Area>
<Name>太宰府市</Name>
<Code>4022100</Code>
</Area>
<ChangeStatus>警報・注意報種別に変化有</ChangeStatus>
</Item>
<Item>
<Kind>
<Name>大雨警報</Name>
<Code>03</Code>
<Status>発表</Status>
<Condition>土砂災害、浸水害</Condition>
<Attention>
<Note>土砂災害警戒</Note>
<Note>浸水警戒</Note>
</Attention>
<Property>
<Type>土砂災害</Type>
<WarningPeriod>
<EndTime>
<Date>２５日</Date>
<Term>昼前</Term>
</EndTime>
</WarningPeriod>
<AdvisoryPeriod>
<EndTime>
<Date>２５日</Date>
<Term>夕方</Term>
</EndTime>
</AdvisoryPeriod>
</Property>
<Property>
<Type>浸水</Type>
<WarningPeriod>
<EndTime>
<Date>２４日</Date>
<Term>夜遅く</Term>
</EndTime>
</WarningPeriod>
<AdvisoryPeriod>
<EndTime>
<Date>２５日</Date>
<Term>朝</Term>
</EndTime>
</AdvisoryPeriod>
<PrecipitationPart>
<Base>
<jmx_eb:Precipitation type="１時間最大雨量" unit="mm" description="８０ミリ">80</jmx_eb:Precipitation>
</Base>
</PrecipitationPart>
</Property>
</Kind>
<Kind>
<Name>洪水警報</Name>
<Code>04</Code>
<Status>発表</Status>
<Addition>
<Note>氾濫</Note>
</Addition>
<Property>
<Type>洪水</Type>
<WarningPeriod>
<EndTime>
<Date>２４日</Date>
<Term>夜遅く</Term>
</EndTime>
</WarningPeriod>
<AdvisoryPeriod>
<EndTime>
<Date>２５日</Date>
<Term>朝</Term>
</EndTime>
</AdvisoryPeriod>
</Property>
</Kind>
<Kind>
<Name>雷注意報</Name>
<Code>14</Code>
<Status>継続</Status>
<Addition>
<Note>竜巻</Note>
</Addition>
<Property>
<Type>雷</Type>
<AdvisoryPeriod>
<EndTime>
<Date>２５日</Date>
<Term>夕方</Term>
</EndTime>
</AdvisoryPeriod>
</Property>
</Kind>
<Kind>
<Name>強風注意報</Name>
<Code>15</Code>
<Status>継続</Status>
<Property>
<Type>風</Type>
<AdvisoryPeriod>
<EndTime>
<Date>２５日</Date>
<Term>夕方</Term>
</EndTime>
</AdvisoryPeriod>
<PeakTime>
<Date>２４日</Date>
<Term>夕方</Term>
</PeakTime>
<WindDirectionPart>
<Base>
<jmx_eb:WindDirection type="風向" unit="８方位漢字" description="南の風">南</jmx_eb:WindDirection>
</Base>
<Becoming>
<jmx_eb:WindDirection type="風向" unit="８方位漢字" description="西の風">西</jmx_eb:WindDirection>
</Becoming>
</WindDirectionPart>
<WindSpeedPart>
<Base>
<Local>
<AreaName>玄界灘</AreaName>
<jmx_eb:WindSpeed type="最大風速" unit="m/s" description="１５メートル">15</jmx_eb:WindSpeed>
</Local>
<Local>
<AreaName>沖ノ島周辺</AreaName>
<jmx_eb:WindSpeed type="最大風速" unit="m/s" description="１５メートル">15</jmx_eb:WindSpeed>
</Local>
</Base>
</WindSpeedPart>
</Property>
</Kind>
<Kind>
<Name>波浪注意報</Name>
<Code>16</Code>
<Status>継続</Status>
<Property>
<Type>波</Type>
<AdvisoryPeriod>
<EndTime>
<Date>２５日</Date>
<Term>夕方</Term>
</EndTime>
</AdvisoryPeriod>
<WaveHeightPart>
<Base>
<Local>
<AreaName>玄界灘</AreaName>
<jmx_eb:WaveHeight type="波高" unit="m" description="２．５メートル">2.5</jmx_eb:WaveHeight>
</Local>
<Local>
<AreaName>沖ノ島周辺</AreaName>
<jmx_eb:WaveHeight type="波高" unit="m" description="２．５メートル">2.5</jmx_eb:WaveHeight>
</Local>
</Base>
</WaveHeightPart>
</Property>
</Kind>
<Area>
<Name>古賀市</Name>
<Code>4022300</Code>
</Area>
<ChangeStatus>警報・注意報種別に変化有</ChangeStatus>
</Item>
<Item>
<Kind>
<Name>大雨警報</Name>
<Code>03</Code>
<Status>発表</Status>
<Condition>土砂災害、浸水害</Condition>
<Attention>
<Note>土砂災害警戒</Note>
<Note>浸水警戒</Note>
</Attention>
<Property>
<Type>土砂災害</Type>
<WarningPeriod>
<EndTime>
<Date>２５日</Date>
<Term>昼前</Term>
</EndTime>
</WarningPeriod>
<AdvisoryPeriod>
<EndTime>
<Date>２５日</Date>
<Term>夕方</Term>
</EndTime>
</AdvisoryPeriod>
</Property>
<Property>
<Type>浸水</Type>
<WarningPeriod>
<EndTime>
<Date>２４日</Date>
<Term>夜遅く</Term>
</EndTime>
</WarningPeriod>
<AdvisoryPeriod>
<EndTime>
<Date>２５日</Date>
<Term>朝</Term>
</EndTime>
</AdvisoryPeriod>
<PrecipitationPart>
<Base>
<jmx_eb:Precipitation type="１時間最大雨量" unit="mm" description="８０ミリ">80</jmx_eb:Precipitation>
</Base>
</PrecipitationPart>
</Property>
</Kind>
<Kind>
<Name>洪水警報</Name>
<Code>04</Code>
<Status>発表</Status>
<Addition>
<Note>氾濫</Note>
</Addition>
<Property>
<Type>洪水</Type>
<WarningPeriod>
<EndTime>
<Date>２４日</Date>
<Term>夜遅く</Term>
</EndTime>
</WarningPeriod>
<AdvisoryPeriod>
<EndTime>
<Date>２５日</Date>
<Term>朝</Term>
</EndTime>
</AdvisoryPeriod>
</Property>
</Kind>
<Kind>
<Name>雷注意報</Name>
<Code>14</Code>
<Status>継続</Status>
<Addition>
<Note>竜巻</Note>
</Addition>
<Property>
<Type>雷</Type>
<AdvisoryPeriod>
<EndTime>
<Date>２５日</Date>
<Term>夕方</Term>
</EndTime>
</AdvisoryPeriod>
</Property>
</Kind>
<Kind>
<Name>強風注意報</Name>
<Code>15</Code>
<Status>継続</Status>
<Property>
<Type>風</Type>
<AdvisoryPeriod>
<EndTime>
<Date>２５日</Date>
<Term>夕方</Term>
</EndTime>
</AdvisoryPeriod>
<PeakTime>
<Date>２４日</Date>
<Term>夕方</Term>
</PeakTime>
<WindDirectionPart>
<Base>
<jmx_eb:WindDirection type="風向" unit="８方位漢字" description="南の風">南</jmx_eb:WindDirection>
</Base>
<Becoming>
<jmx_eb:WindDirection type="風向" unit="８方位漢字" description="西の風">西</jmx_eb:WindDirection>
</Becoming>
</WindDirectionPart>
<WindSpeedPart>
<Base>
<Local>
<AreaName>玄界灘</AreaName>
<jmx_eb:WindSpeed type="最大風速" unit="m/s" description="１５メートル">15</jmx_eb:WindSpeed>
</Local>
<Local>
<AreaName>沖ノ島周辺</AreaName>
<jmx_eb:WindSpeed type="最大風速" unit="m/s" description="１５メートル">15</jmx_eb:WindSpeed>
</Local>
</Base>
</WindSpeedPart>
</Property>
</Kind>
<Kind>
<Name>波浪注意報</Name>
<Code>16</Code>
<Status>継続</Status>
<Property>
<Type>波</Type>
<AdvisoryPeriod>
<EndTime>
<Date>２５日</Date>
<Term>夕方</Term>
</EndTime>
</AdvisoryPeriod>
<WaveHeightPart>
<Base>
<Local>
<AreaName>玄界灘</AreaName>
<jmx_eb:WaveHeight type="波高" unit="m" description="２．５メートル">2.5</jmx_eb:WaveHeight>
</Local>
<Local>
<AreaName>沖ノ島周辺</AreaName>
<jmx_eb:WaveHeight type="波高" unit="m" description="２．５メートル">2.5</jmx_eb:WaveHeight>
</Local>
</Base>
</WaveHeightPart>
</Property>
</Kind>
<Area>
<Name>福津市</Name>
<Code>4022400</Code>
</Area>
<ChangeStatus>警報・注意報種別に変化有</ChangeStatus>
</Item>
<Item>
<Kind>
<Name>雷注意報</Name>
<Code>14</Code>
<Status>継続</Status>
<Addition>
<Note>竜巻</Note>
</Addition>
<Property>
<Type>雷</Type>
<AdvisoryPeriod>
<EndTime>
<Date>２５日</Date>
<Term>夕方</Term>
</EndTime>
</AdvisoryPeriod>
</Property>
</Kind>
<Area>
<Name>うきは市</Name>
<Code>4022500</Code>
</Area>
<ChangeStatus>警報・注意報種別に変化無、量的予想事項等に変化有</ChangeStatus>
</Item>
<Item>
<Kind>
<Name>雷注意報</Name>
<Code>14</Code>
<Status>継続</Status>
<Addition>
<Note>竜巻</Note>
</Addition>
<Property>
<Type>雷</Type>
<AdvisoryPeriod>
<EndTime>
<Date>２５日</Date>
<Term>夕方</Term>
</EndTime>
</AdvisoryPeriod>
</Property>
</Kind>
<Area>
<Name>宮若市</Name>
<Code>4022600</Code>
</Area>
<ChangeStatus>警報・注意報種別に変化無、量的予想事項等に変化有</ChangeStatus>
</Item>
<Item>
<Kind>
<Name>雷注意報</Name>
<Code>14</Code>
<Status>継続</Status>
<Addition>
<Note>竜巻</Note>
</Addition>
<Property>
<Type>雷</Type>
<AdvisoryPeriod>
<EndTime>
<Date>２５日</Date>
<Term>夕方</Term>
</EndTime>
</AdvisoryPeriod>
</Property>
</Kind>
<Area>
<Name>嘉麻市</Name>
<Code>4022700</Code>
</Area>
<ChangeStatus>警報・注意報種別に変化無、量的予想事項等に変化有</ChangeStatus>
</Item>
<Item>
<Kind>
<Name>雷注意報</Name>
<Code>14</Code>
<Status>継続</Status>
<Addition>
<Note>竜巻</Note>
</Addition>
<Property>
<Type>雷</Type>
<AdvisoryPeriod>
<EndTime>
<Date>２５日</Date>
<Term>夕方</Term>
</EndTime>
</AdvisoryPeriod>
</Property>
</Kind>
<Area>
<Name>朝倉市</Name>
<Code>4022800</Code>
</Area>
<ChangeStatus>警報・注意報種別に変化無、量的予想事項等に変化有</ChangeStatus>
</Item>
<Item>
<Kind>
<Name>雷注意報</Name>
<Code>14</Code>
<Status>継続</Status>
<Addition>
<Note>竜巻</Note>
</Addition>
<Property>
<Type>雷</Type>
<AdvisoryPeriod>
<EndTime>
<Date>２５日</Date>
<Term>夕方</Term>
</EndTime>
</AdvisoryPeriod>
</Property>
</Kind>
<Kind>
<Name>強風注意報</Name>
<Code>15</Code>
<Status>継続</Status>
<Property>
<Type>風</Type>
<AdvisoryPeriod>
<EndTime>
<Date>２４日</Date>
<Term>夜のはじめ頃</Term>
</EndTime>
</AdvisoryPeriod>
<WindDirectionPart>
<Base>
<jmx_eb:WindDirection type="風向" unit="８方位漢字" description="南の風">南</jmx_eb:WindDirection>
</Base>
</WindDirectionPart>
<WindSpeedPart>
<Base>
<Local>
<AreaName>海上</AreaName>
<jmx_eb:WindSpeed type="最大風速" unit="m/s" description="１２メートル">12</jmx_eb:WindSpeed>
</Local>
</Base>
</WindSpeedPart>
</Property>
</Kind>
<Area>
<Name>みやま市</Name>
<Code>4022900</Code>
</Area>
<ChangeStatus>警報・注意報種別に変化無、量的予想事項等に変化有</ChangeStatus>
</Item>
<Item>
<Kind>
<Name>大雨警報</Name>
<Code>03</Code>
<Status>発表</Status>
<Condition>土砂災害、浸水害</Condition>
<Attention>
<Note>土砂災害警戒</Note>
<Note>浸水警戒</Note>
</Attention>
<Property>
<Type>土砂災害</Type>
<WarningPeriod>
<EndTime>
<Date>２５日</Date>
<Term>昼前</Term>
</EndTime>
</WarningPeriod>
<AdvisoryPeriod>
<EndTime>
<Date>２５日</Date>
<Term>夕方</Term>
</EndTime>
</AdvisoryPeriod>
</Property>
<Property>
<Type>浸水</Type>
<WarningPeriod>
<EndTime>
<Date>２４日</Date>
<Term>夜遅く</Term>
</EndTime>
</WarningPeriod>
<AdvisoryPeriod>
<EndTime>
<Date>２５日</Date>
<Term>朝</Term>
</EndTime>
</AdvisoryPeriod>
<PrecipitationPart>
<Base>
<jmx_eb:Precipitation type="１時間最大雨量" unit="mm" description="８０ミリ">80</jmx_eb:Precipitation>
</Base>
</PrecipitationPart>
</Property>
</Kind>
<Kind>
<Name>洪水警報</Name>
<Code>04</Code>
<Status>発表</Status>
<Addition>
<Note>氾濫</Note>
</Addition>
<Property>
<Type>洪水</Type>
<WarningPeriod>
<EndTime>
<Date>２４日</Date>
<Term>夜遅く</Term>
</EndTime>
</WarningPeriod>
<AdvisoryPeriod>
<EndTime>
<Date>２５日</Date>
<Term>朝</Term>
</EndTime>
</AdvisoryPeriod>
</Property>
</Kind>
<Kind>
<Name>雷注意報</Name>
<Code>14</Code>
<Status>継続</Status>
<Addition>
<Note>竜巻</Note>
</Addition>
<Property>
<Type>雷</Type>
<AdvisoryPeriod>
<EndTime>
<Date>２５日</Date>
<Term>夕方</Term>
</EndTime>
</AdvisoryPeriod>
</Property>
</Kind>
<Kind>
<Name>強風注意報</Name>
<Code>15</Code>
<Status>継続</Status>
<Property>
<Type>風</Type>
<AdvisoryPeriod>
<EndTime>
<Date>２５日</Date>
<Term>夕方</Term>
</EndTime>
</AdvisoryPeriod>
<PeakTime>
<Date>２４日</Date>
<Term>夕方</Term>
</PeakTime>
<WindDirectionPart>
<Base>
<jmx_eb:WindDirection type="風向" unit="８方位漢字" description="南の風">南</jmx_eb:WindDirection>
</Base>
<Becoming>
<jmx_eb:WindDirection type="風向" unit="８方位漢字" description="西の風">西</jmx_eb:WindDirection>
</Becoming>
</WindDirectionPart>
<WindSpeedPart>
<Base>
<Local>
<AreaName>玄界灘</AreaName>
<jmx_eb:WindSpeed type="最大風速" unit="m/s" description="１５メートル">15</jmx_eb:WindSpeed>
</Local>
<Local>
<AreaName>沖ノ島周辺</AreaName>
<jmx_eb:WindSpeed type="最大風速" unit="m/s" description="１５メートル">15</jmx_eb:WindSpeed>
</Local>
</Base>
</WindSpeedPart>
</Property>
</Kind>
<Kind>
<Name>波浪注意報</Name>
<Code>16</Code>
<Status>継続</Status>
<Property>
<Type>波</Type>
<AdvisoryPeriod>
<EndTime>
<Date>２５日</Date>
<Term>夕方</Term>
</EndTime>
</AdvisoryPeriod>
<WaveHeightPart>
<Base>
<Local>
<AreaName>玄界灘</AreaName>
<jmx_eb:WaveHeight type="波高" unit="m" description="２．５メートル">2.5</jmx_eb:WaveHeight>
</Local>
<Local>
<AreaName>沖ノ島周辺</AreaName>
<jmx_eb:WaveHeight type="波高" unit="m" description="２．５メートル">2.5</jmx_eb:WaveHeight>
</Local>
</Base>
</WaveHeightPart>
</Property>
</Kind>
<Area>
<Name>糸島市</Name>
<Code>4023000</Code>
</Area>
<ChangeStatus>警報・注意報種別に変化有</ChangeStatus>
</Item>
<Item>
<Kind>
<Name>大雨警報</Name>
<Code>03</Code>
<Status>発表</Status>
<Condition>土砂災害、浸水害</Condition>
<Attention>
<Note>土砂災害警戒</Note>
<Note>浸水警戒</Note>
</Attention>
<Property>
<Type>土砂災害</Type>
<WarningPeriod>
<EndTime>
<Date>２５日</Date>
<Term>昼前</Term>
</EndTime>
</WarningPeriod>
<AdvisoryPeriod>
<EndTime>
<Date>２５日</Date>
<Term>夕方</Term>
</EndTime>
</AdvisoryPeriod>
</Property>
<Property>
<Type>浸水</Type>
<WarningPeriod>
<EndTime>
<Date>２４日</Date>
<Term>夜遅く</Term>
</EndTime>
</WarningPeriod>
<AdvisoryPeriod>
<EndTime>
<Date>２５日</Date>
<Term>朝</Term>
</EndTime>
</AdvisoryPeriod>
<PrecipitationPart>
<Base>
<jmx_eb:Precipitation type="１時間最大雨量" unit="mm" description="８０ミリ">80</jmx_eb:Precipitation>
</Base>
</PrecipitationPart>
</Property>
</Kind>
<Kind>
<Name>洪水警報</Name>
<Code>04</Code>
<Status>発表</Status>
<Addition>
<Note>氾濫</Note>
</Addition>
<Property>
<Type>洪水</Type>
<WarningPeriod>
<EndTime>
<Date>２４日</Date>
<Term>夜遅く</Term>
</EndTime>
</WarningPeriod>
<AdvisoryPeriod>
<EndTime>
<Date>２５日</Date>
<Term>朝</Term>
</EndTime>
</AdvisoryPeriod>
</Property>
</Kind>
<Kind>
<Name>雷注意報</Name>
<Code>14</Code>
<Status>継続</Status>
<Addition>
<Note>竜巻</Note>
</Addition>
<Property>
<Type>雷</Type>
<AdvisoryPeriod>
<EndTime>
<Date>２５日</Date>
<Term>夕方</Term>
</EndTime>
</AdvisoryPeriod>
</Property>
</Kind>
<Area>
<Name>那珂川町</Name>
<Code>4030500</Code>
</Area>
<ChangeStatus>警報・注意報種別に変化有</ChangeStatus>
</Item>
<Item>
<Kind>
<Name>大雨警報</Name>
<Code>03</Code>
<Status>発表</Status>
<Condition>土砂災害、浸水害</Condition>
<Attention>
<Note>土砂災害警戒</Note>
<Note>浸水警戒</Note>
</Attention>
<Property>
<Type>土砂災害</Type>
<WarningPeriod>
<EndTime>
<Date>２５日</Date>
<Term>昼前</Term>
</EndTime>
</WarningPeriod>
<AdvisoryPeriod>
<EndTime>
<Date>２５日</Date>
<Term>夕方</Term>
</EndTime>
</AdvisoryPeriod>
</Property>
<Property>
<Type>浸水</Type>
<WarningPeriod>
<EndTime>
<Date>２４日</Date>
<Term>夜遅く</Term>
</EndTime>
</WarningPeriod>
<AdvisoryPeriod>
<EndTime>
<Date>２５日</Date>
<Term>朝</Term>
</EndTime>
</AdvisoryPeriod>
<PrecipitationPart>
<Base>
<jmx_eb:Precipitation type="１時間最大雨量" unit="mm" description="８０ミリ">80</jmx_eb:Precipitation>
</Base>
</PrecipitationPart>
</Property>
</Kind>
<Kind>
<Name>洪水警報</Name>
<Code>04</Code>
<Status>発表</Status>
<Addition>
<Note>氾濫</Note>
</Addition>
<Property>
<Type>洪水</Type>
<WarningPeriod>
<EndTime>
<Date>２４日</Date>
<Term>夜遅く</Term>
</EndTime>
</WarningPeriod>
<AdvisoryPeriod>
<EndTime>
<Date>２５日</Date>
<Term>朝</Term>
</EndTime>
</AdvisoryPeriod>
</Property>
</Kind>
<Kind>
<Name>雷注意報</Name>
<Code>14</Code>
<Status>継続</Status>
<Addition>
<Note>竜巻</Note>
</Addition>
<Property>
<Type>雷</Type>
<AdvisoryPeriod>
<EndTime>
<Date>２５日</Date>
<Term>夕方</Term>
</EndTime>
</AdvisoryPeriod>
</Property>
</Kind>
<Area>
<Name>宇美町</Name>
<Code>4034100</Code>
</Area>
<ChangeStatus>警報・注意報種別に変化有</ChangeStatus>
</Item>
<Item>
<Kind>
<Name>大雨警報</Name>
<Code>03</Code>
<Status>発表</Status>
<Condition>土砂災害、浸水害</Condition>
<Attention>
<Note>土砂災害警戒</Note>
<Note>浸水警戒</Note>
</Attention>
<Property>
<Type>土砂災害</Type>
<WarningPeriod>
<EndTime>
<Date>２５日</Date>
<Term>昼前</Term>
</EndTime>
</WarningPeriod>
<AdvisoryPeriod>
<EndTime>
<Date>２５日</Date>
<Term>夕方</Term>
</EndTime>
</AdvisoryPeriod>
</Property>
<Property>
<Type>浸水</Type>
<WarningPeriod>
<EndTime>
<Date>２４日</Date>
<Term>夜遅く</Term>
</EndTime>
</WarningPeriod>
<AdvisoryPeriod>
<EndTime>
<Date>２５日</Date>
<Term>朝</Term>
</EndTime>
</AdvisoryPeriod>
<PrecipitationPart>
<Base>
<jmx_eb:Precipitation type="１時間最大雨量" unit="mm" description="８０ミリ">80</jmx_eb:Precipitation>
</Base>
</PrecipitationPart>
</Property>
</Kind>
<Kind>
<Name>洪水警報</Name>
<Code>04</Code>
<Status>発表</Status>
<Addition>
<Note>氾濫</Note>
</Addition>
<Property>
<Type>洪水</Type>
<WarningPeriod>
<EndTime>
<Date>２４日</Date>
<Term>夜遅く</Term>
</EndTime>
</WarningPeriod>
<AdvisoryPeriod>
<EndTime>
<Date>２５日</Date>
<Term>朝</Term>
</EndTime>
</AdvisoryPeriod>
</Property>
</Kind>
<Kind>
<Name>雷注意報</Name>
<Code>14</Code>
<Status>継続</Status>
<Addition>
<Note>竜巻</Note>
</Addition>
<Property>
<Type>雷</Type>
<AdvisoryPeriod>
<EndTime>
<Date>２５日</Date>
<Term>夕方</Term>
</EndTime>
</AdvisoryPeriod>
</Property>
</Kind>
<Area>
<Name>篠栗町</Name>
<Code>4034200</Code>
</Area>
<ChangeStatus>警報・注意報種別に変化有</ChangeStatus>
</Item>
<Item>
<Kind>
<Name>大雨警報</Name>
<Code>03</Code>
<Status>発表</Status>
<Condition>土砂災害、浸水害</Condition>
<Attention>
<Note>土砂災害警戒</Note>
<Note>浸水警戒</Note>
</Attention>
<Property>
<Type>土砂災害</Type>
<WarningPeriod>
<EndTime>
<Date>２５日</Date>
<Term>昼前</Term>
</EndTime>
</WarningPeriod>
<AdvisoryPeriod>
<EndTime>
<Date>２５日</Date>
<Term>夕方</Term>
</EndTime>
</AdvisoryPeriod>
</Property>
<Property>
<Type>浸水</Type>
<WarningPeriod>
<EndTime>
<Date>２４日</Date>
<Term>夜遅く</Term>
</EndTime>
</WarningPeriod>
<AdvisoryPeriod>
<EndTime>
<Date>２５日</Date>
<Term>朝</Term>
</EndTime>
</AdvisoryPeriod>
<PrecipitationPart>
<Base>
<jmx_eb:Precipitation type="１時間最大雨量" unit="mm" description="８０ミリ">80</jmx_eb:Precipitation>
</Base>
</PrecipitationPart>
</Property>
</Kind>
<Kind>
<Name>洪水警報</Name>
<Code>04</Code>
<Status>発表</Status>
<Addition>
<Note>氾濫</Note>
</Addition>
<Property>
<Type>洪水</Type>
<WarningPeriod>
<EndTime>
<Date>２４日</Date>
<Term>夜遅く</Term>
</EndTime>
</WarningPeriod>
<AdvisoryPeriod>
<EndTime>
<Date>２５日</Date>
<Term>朝</Term>
</EndTime>
</AdvisoryPeriod>
</Property>
</Kind>
<Kind>
<Name>雷注意報</Name>
<Code>14</Code>
<Status>継続</Status>
<Addition>
<Note>竜巻</Note>
</Addition>
<Property>
<Type>雷</Type>
<AdvisoryPeriod>
<EndTime>
<Date>２５日</Date>
<Term>夕方</Term>
</EndTime>
</AdvisoryPeriod>
</Property>
</Kind>
<Area>
<Name>志免町</Name>
<Code>4034300</Code>
</Area>
<ChangeStatus>警報・注意報種別に変化有</ChangeStatus>
</Item>
<Item>
<Kind>
<Name>大雨警報</Name>
<Code>03</Code>
<Status>発表</Status>
<Condition>土砂災害、浸水害</Condition>
<Attention>
<Note>土砂災害警戒</Note>
<Note>浸水警戒</Note>
</Attention>
<Property>
<Type>土砂災害</Type>
<WarningPeriod>
<EndTime>
<Date>２５日</Date>
<Term>昼前</Term>
</EndTime>
</WarningPeriod>
<AdvisoryPeriod>
<EndTime>
<Date>２５日</Date>
<Term>夕方</Term>
</EndTime>
</AdvisoryPeriod>
</Property>
<Property>
<Type>浸水</Type>
<WarningPeriod>
<EndTime>
<Date>２４日</Date>
<Term>夜遅く</Term>
</EndTime>
</WarningPeriod>
<AdvisoryPeriod>
<EndTime>
<Date>２５日</Date>
<Term>朝</Term>
</EndTime>
</AdvisoryPeriod>
<PrecipitationPart>
<Base>
<jmx_eb:Precipitation type="１時間最大雨量" unit="mm" description="８０ミリ">80</jmx_eb:Precipitation>
</Base>
</PrecipitationPart>
</Property>
</Kind>
<Kind>
<Name>洪水警報</Name>
<Code>04</Code>
<Status>発表</Status>
<Addition>
<Note>氾濫</Note>
</Addition>
<Property>
<Type>洪水</Type>
<WarningPeriod>
<EndTime>
<Date>２４日</Date>
<Term>夜遅く</Term>
</EndTime>
</WarningPeriod>
<AdvisoryPeriod>
<EndTime>
<Date>２５日</Date>
<Term>朝</Term>
</EndTime>
</AdvisoryPeriod>
</Property>
</Kind>
<Kind>
<Name>雷注意報</Name>
<Code>14</Code>
<Status>継続</Status>
<Addition>
<Note>竜巻</Note>
</Addition>
<Property>
<Type>雷</Type>
<AdvisoryPeriod>
<EndTime>
<Date>２５日</Date>
<Term>夕方</Term>
</EndTime>
</AdvisoryPeriod>
</Property>
</Kind>
<Area>
<Name>須恵町</Name>
<Code>4034400</Code>
</Area>
<ChangeStatus>警報・注意報種別に変化有</ChangeStatus>
</Item>
<Item>
<Kind>
<Name>大雨警報</Name>
<Code>03</Code>
<Status>発表</Status>
<Condition>土砂災害、浸水害</Condition>
<Attention>
<Note>土砂災害警戒</Note>
<Note>浸水警戒</Note>
</Attention>
<Property>
<Type>土砂災害</Type>
<WarningPeriod>
<EndTime>
<Date>２５日</Date>
<Term>昼前</Term>
</EndTime>
</WarningPeriod>
<AdvisoryPeriod>
<EndTime>
<Date>２５日</Date>
<Term>夕方</Term>
</EndTime>
</AdvisoryPeriod>
</Property>
<Property>
<Type>浸水</Type>
<WarningPeriod>
<EndTime>
<Date>２４日</Date>
<Term>夜遅く</Term>
</EndTime>
</WarningPeriod>
<AdvisoryPeriod>
<EndTime>
<Date>２５日</Date>
<Term>朝</Term>
</EndTime>
</AdvisoryPeriod>
<PrecipitationPart>
<Base>
<jmx_eb:Precipitation type="１時間最大雨量" unit="mm" description="８０ミリ">80</jmx_eb:Precipitation>
</Base>
</PrecipitationPart>
</Property>
</Kind>
<Kind>
<Name>洪水警報</Name>
<Code>04</Code>
<Status>発表</Status>
<Addition>
<Note>氾濫</Note>
</Addition>
<Property>
<Type>洪水</Type>
<WarningPeriod>
<EndTime>
<Date>２４日</Date>
<Term>夜遅く</Term>
</EndTime>
</WarningPeriod>
<AdvisoryPeriod>
<EndTime>
<Date>２５日</Date>
<Term>朝</Term>
</EndTime>
</AdvisoryPeriod>
</Property>
</Kind>
<Kind>
<Name>雷注意報</Name>
<Code>14</Code>
<Status>継続</Status>
<Addition>
<Note>竜巻</Note>
</Addition>
<Property>
<Type>雷</Type>
<AdvisoryPeriod>
<EndTime>
<Date>２５日</Date>
<Term>夕方</Term>
</EndTime>
</AdvisoryPeriod>
</Property>
</Kind>
<Kind>
<Name>強風注意報</Name>
<Code>15</Code>
<Status>継続</Status>
<Property>
<Type>風</Type>
<AdvisoryPeriod>
<EndTime>
<Date>２５日</Date>
<Term>夕方</Term>
</EndTime>
</AdvisoryPeriod>
<PeakTime>
<Date>２４日</Date>
<Term>夕方</Term>
</PeakTime>
<WindDirectionPart>
<Base>
<jmx_eb:WindDirection type="風向" unit="８方位漢字" description="南の風">南</jmx_eb:WindDirection>
</Base>
<Becoming>
<jmx_eb:WindDirection type="風向" unit="８方位漢字" description="西の風">西</jmx_eb:WindDirection>
</Becoming>
</WindDirectionPart>
<WindSpeedPart>
<Base>
<Local>
<AreaName>玄界灘</AreaName>
<jmx_eb:WindSpeed type="最大風速" unit="m/s" description="１５メートル">15</jmx_eb:WindSpeed>
</Local>
<Local>
<AreaName>沖ノ島周辺</AreaName>
<jmx_eb:WindSpeed type="最大風速" unit="m/s" description="１５メートル">15</jmx_eb:WindSpeed>
</Local>
</Base>
</WindSpeedPart>
</Property>
</Kind>
<Kind>
<Name>波浪注意報</Name>
<Code>16</Code>
<Status>継続</Status>
<Property>
<Type>波</Type>
<AdvisoryPeriod>
<EndTime>
<Date>２５日</Date>
<Term>夕方</Term>
</EndTime>
</AdvisoryPeriod>
<WaveHeightPart>
<Base>
<Local>
<AreaName>玄界灘</AreaName>
<jmx_eb:WaveHeight type="波高" unit="m" description="２．５メートル">2.5</jmx_eb:WaveHeight>
</Local>
<Local>
<AreaName>沖ノ島周辺</AreaName>
<jmx_eb:WaveHeight type="波高" unit="m" description="２．５メートル">2.5</jmx_eb:WaveHeight>
</Local>
</Base>
</WaveHeightPart>
</Property>
</Kind>
<Area>
<Name>新宮町</Name>
<Code>4034500</Code>
</Area>
<ChangeStatus>警報・注意報種別に変化有</ChangeStatus>
</Item>
<Item>
<Kind>
<Name>大雨警報</Name>
<Code>03</Code>
<Status>発表</Status>
<Condition>土砂災害、浸水害</Condition>
<Attention>
<Note>土砂災害警戒</Note>
<Note>浸水警戒</Note>
</Attention>
<Property>
<Type>土砂災害</Type>
<WarningPeriod>
<EndTime>
<Date>２５日</Date>
<Term>昼前</Term>
</EndTime>
</WarningPeriod>
<AdvisoryPeriod>
<EndTime>
<Date>２５日</Date>
<Term>夕方</Term>
</EndTime>
</AdvisoryPeriod>
</Property>
<Property>
<Type>浸水</Type>
<WarningPeriod>
<EndTime>
<Date>２４日</Date>
<Term>夜遅く</Term>
</EndTime>
</WarningPeriod>
<AdvisoryPeriod>
<EndTime>
<Date>２５日</Date>
<Term>朝</Term>
</EndTime>
</AdvisoryPeriod>
<PrecipitationPart>
<Base>
<jmx_eb:Precipitation type="１時間最大雨量" unit="mm" description="８０ミリ">80</jmx_eb:Precipitation>
</Base>
</PrecipitationPart>
</Property>
</Kind>
<Kind>
<Name>洪水警報</Name>
<Code>04</Code>
<Status>発表</Status>
<Addition>
<Note>氾濫</Note>
</Addition>
<Property>
<Type>洪水</Type>
<WarningPeriod>
<EndTime>
<Date>２４日</Date>
<Term>夜遅く</Term>
</EndTime>
</WarningPeriod>
<AdvisoryPeriod>
<EndTime>
<Date>２５日</Date>
<Term>朝</Term>
</EndTime>
</AdvisoryPeriod>
</Property>
</Kind>
<Kind>
<Name>雷注意報</Name>
<Code>14</Code>
<Status>継続</Status>
<Addition>
<Note>竜巻</Note>
</Addition>
<Property>
<Type>雷</Type>
<AdvisoryPeriod>
<EndTime>
<Date>２５日</Date>
<Term>夕方</Term>
</EndTime>
</AdvisoryPeriod>
</Property>
</Kind>
<Area>
<Name>久山町</Name>
<Code>4034800</Code>
</Area>
<ChangeStatus>警報・注意報種別に変化有</ChangeStatus>
</Item>
<Item>
<Kind>
<Name>大雨警報</Name>
<Code>03</Code>
<Status>発表</Status>
<Condition>土砂災害、浸水害</Condition>
<Attention>
<Note>土砂災害警戒</Note>
<Note>浸水警戒</Note>
</Attention>
<Property>
<Type>土砂災害</Type>
<WarningPeriod>
<EndTime>
<Date>２５日</Date>
<Term>昼前</Term>
</EndTime>
</WarningPeriod>
<AdvisoryPeriod>
<EndTime>
<Date>２５日</Date>
<Term>夕方</Term>
</EndTime>
</AdvisoryPeriod>
</Property>
<Property>
<Type>浸水</Type>
<WarningPeriod>
<EndTime>
<Date>２４日</Date>
<Term>夜遅く</Term>
</EndTime>
</WarningPeriod>
<AdvisoryPeriod>
<EndTime>
<Date>２５日</Date>
<Term>朝</Term>
</EndTime>
</AdvisoryPeriod>
<PrecipitationPart>
<Base>
<jmx_eb:Precipitation type="１時間最大雨量" unit="mm" description="８０ミリ">80</jmx_eb:Precipitation>
</Base>
</PrecipitationPart>
</Property>
</Kind>
<Kind>
<Name>洪水警報</Name>
<Code>04</Code>
<Status>発表</Status>
<Addition>
<Note>氾濫</Note>
</Addition>
<Property>
<Type>洪水</Type>
<WarningPeriod>
<EndTime>
<Date>２４日</Date>
<Term>夜遅く</Term>
</EndTime>
</WarningPeriod>
<AdvisoryPeriod>
<EndTime>
<Date>２５日</Date>
<Term>朝</Term>
</EndTime>
</AdvisoryPeriod>
</Property>
</Kind>
<Kind>
<Name>雷注意報</Name>
<Code>14</Code>
<Status>継続</Status>
<Addition>
<Note>竜巻</Note>
</Addition>
<Property>
<Type>雷</Type>
<AdvisoryPeriod>
<EndTime>
<Date>２５日</Date>
<Term>夕方</Term>
</EndTime>
</AdvisoryPeriod>
</Property>
</Kind>
<Area>
<Name>粕屋町</Name>
<Code>4034900</Code>
</Area>
<ChangeStatus>警報・注意報種別に変化有</ChangeStatus>
</Item>
<Item>
<Kind>
<Name>大雨警報</Name>
<Code>03</Code>
<Status>発表</Status>
<Condition>土砂災害、浸水害</Condition>
<Attention>
<Note>土砂災害警戒</Note>
<Note>浸水警戒</Note>
</Attention>
<Property>
<Type>土砂災害</Type>
<WarningPeriod>
<EndTime>
<Date>２５日</Date>
<Term>昼前</Term>
</EndTime>
</WarningPeriod>
<AdvisoryPeriod>
<EndTime>
<Date>２５日</Date>
<Term>夕方</Term>
</EndTime>
</AdvisoryPeriod>
</Property>
<Property>
<Type>浸水</Type>
<WarningPeriod>
<EndTime>
<Date>２４日</Date>
<Term>夜遅く</Term>
</EndTime>
</WarningPeriod>
<AdvisoryPeriod>
<EndTime>
<Date>２５日</Date>
<Term>朝</Term>
</EndTime>
</AdvisoryPeriod>
<PrecipitationPart>
<Base>
<jmx_eb:Precipitation type="１時間最大雨量" unit="mm" description="８０ミリ">80</jmx_eb:Precipitation>
</Base>
</PrecipitationPart>
</Property>
</Kind>
<Kind>
<Name>洪水警報</Name>
<Code>04</Code>
<Status>発表</Status>
<Addition>
<Note>氾濫</Note>
</Addition>
<Property>
<Type>洪水</Type>
<WarningPeriod>
<EndTime>
<Date>２４日</Date>
<Term>夜遅く</Term>
</EndTime>
</WarningPeriod>
<AdvisoryPeriod>
<EndTime>
<Date>２５日</Date>
<Term>朝</Term>
</EndTime>
</AdvisoryPeriod>
</Property>
</Kind>
<Kind>
<Name>雷注意報</Name>
<Code>14</Code>
<Status>継続</Status>
<Addition>
<Note>竜巻</Note>
</Addition>
<Property>
<Type>雷</Type>
<AdvisoryPeriod>
<EndTime>
<Date>２５日</Date>
<Term>夕方</Term>
</EndTime>
</AdvisoryPeriod>
</Property>
</Kind>
<Kind>
<Name>強風注意報</Name>
<Code>15</Code>
<Status>継続</Status>
<Property>
<Type>風</Type>
<AdvisoryPeriod>
<EndTime>
<Date>２５日</Date>
<Term>夕方</Term>
</EndTime>
</AdvisoryPeriod>
<PeakTime>
<Date>２４日</Date>
<Term>夕方</Term>
</PeakTime>
<WindDirectionPart>
<Base>
<jmx_eb:WindDirection type="風向" unit="８方位漢字" description="南の風">南</jmx_eb:WindDirection>
</Base>
</WindDirectionPart>
<WindSpeedPart>
<Base>
<Local>
<AreaName>海上</AreaName>
<jmx_eb:WindSpeed type="最大風速" unit="m/s" description="１５メートル">15</jmx_eb:WindSpeed>
</Local>
</Base>
</WindSpeedPart>
</Property>
</Kind>
<Kind>
<Name>波浪注意報</Name>
<Code>16</Code>
<Status>継続</Status>
<Property>
<Type>波</Type>
<AdvisoryPeriod>
<EndTime>
<Date>２５日</Date>
<Term>夕方</Term>
</EndTime>
</AdvisoryPeriod>
<WaveHeightPart>
<Base>
<jmx_eb:WaveHeight type="波高" unit="m" description="２．５メートル">2.5</jmx_eb:WaveHeight>
</Base>
</WaveHeightPart>
</Property>
</Kind>
<Area>
<Name>芦屋町</Name>
<Code>4038100</Code>
</Area>
<ChangeStatus>警報・注意報種別に変化有</ChangeStatus>
</Item>
<Item>
<Kind>
<Name>大雨警報</Name>
<Code>03</Code>
<Status>発表</Status>
<Condition>土砂災害、浸水害</Condition>
<Attention>
<Note>土砂災害警戒</Note>
<Note>浸水警戒</Note>
</Attention>
<Property>
<Type>土砂災害</Type>
<WarningPeriod>
<EndTime>
<Date>２５日</Date>
<Term>昼前</Term>
</EndTime>
</WarningPeriod>
<AdvisoryPeriod>
<EndTime>
<Date>２５日</Date>
<Term>夕方</Term>
</EndTime>
</AdvisoryPeriod>
</Property>
<Property>
<Type>浸水</Type>
<WarningPeriod>
<EndTime>
<Date>２４日</Date>
<Term>夜遅く</Term>
</EndTime>
</WarningPeriod>
<AdvisoryPeriod>
<EndTime>
<Date>２５日</Date>
<Term>朝</Term>
</EndTime>
</AdvisoryPeriod>
<PrecipitationPart>
<Base>
<jmx_eb:Precipitation type="１時間最大雨量" unit="mm" description="８０ミリ">80</jmx_eb:Precipitation>
</Base>
</PrecipitationPart>
</Property>
</Kind>
<Kind>
<Name>洪水警報</Name>
<Code>04</Code>
<Status>発表</Status>
<Addition>
<Note>氾濫</Note>
</Addition>
<Property>
<Type>洪水</Type>
<WarningPeriod>
<EndTime>
<Date>２４日</Date>
<Term>夜遅く</Term>
</EndTime>
</WarningPeriod>
<AdvisoryPeriod>
<EndTime>
<Date>２５日</Date>
<Term>朝</Term>
</EndTime>
</AdvisoryPeriod>
</Property>
</Kind>
<Kind>
<Name>雷注意報</Name>
<Code>14</Code>
<Status>継続</Status>
<Addition>
<Note>竜巻</Note>
</Addition>
<Property>
<Type>雷</Type>
<AdvisoryPeriod>
<EndTime>
<Date>２５日</Date>
<Term>夕方</Term>
</EndTime>
</AdvisoryPeriod>
</Property>
</Kind>
<Area>
<Name>水巻町</Name>
<Code>4038200</Code>
</Area>
<ChangeStatus>警報・注意報種別に変化有</ChangeStatus>
</Item>
<Item>
<Kind>
<Name>大雨警報</Name>
<Code>03</Code>
<Status>発表</Status>
<Condition>土砂災害、浸水害</Condition>
<Attention>
<Note>土砂災害警戒</Note>
<Note>浸水警戒</Note>
</Attention>
<Property>
<Type>土砂災害</Type>
<WarningPeriod>
<EndTime>
<Date>２５日</Date>
<Term>昼前</Term>
</EndTime>
</WarningPeriod>
<AdvisoryPeriod>
<EndTime>
<Date>２５日</Date>
<Term>夕方</Term>
</EndTime>
</AdvisoryPeriod>
</Property>
<Property>
<Type>浸水</Type>
<WarningPeriod>
<EndTime>
<Date>２４日</Date>
<Term>夜遅く</Term>
</EndTime>
</WarningPeriod>
<AdvisoryPeriod>
<EndTime>
<Date>２５日</Date>
<Term>朝</Term>
</EndTime>
</AdvisoryPeriod>
<PrecipitationPart>
<Base>
<jmx_eb:Precipitation type="１時間最大雨量" unit="mm" description="８０ミリ">80</jmx_eb:Precipitation>
</Base>
</PrecipitationPart>
</Property>
</Kind>
<Kind>
<Name>洪水警報</Name>
<Code>04</Code>
<Status>発表</Status>
<Addition>
<Note>氾濫</Note>
</Addition>
<Property>
<Type>洪水</Type>
<WarningPeriod>
<EndTime>
<Date>２４日</Date>
<Term>夜遅く</Term>
</EndTime>
</WarningPeriod>
<AdvisoryPeriod>
<EndTime>
<Date>２５日</Date>
<Term>朝</Term>
</EndTime>
</AdvisoryPeriod>
</Property>
</Kind>
<Kind>
<Name>雷注意報</Name>
<Code>14</Code>
<Status>継続</Status>
<Addition>
<Note>竜巻</Note>
</Addition>
<Property>
<Type>雷</Type>
<AdvisoryPeriod>
<EndTime>
<Date>２５日</Date>
<Term>夕方</Term>
</EndTime>
</AdvisoryPeriod>
</Property>
</Kind>
<Kind>
<Name>強風注意報</Name>
<Code>15</Code>
<Status>継続</Status>
<Property>
<Type>風</Type>
<AdvisoryPeriod>
<EndTime>
<Date>２５日</Date>
<Term>夕方</Term>
</EndTime>
</AdvisoryPeriod>
<PeakTime>
<Date>２４日</Date>
<Term>夕方</Term>
</PeakTime>
<WindDirectionPart>
<Base>
<jmx_eb:WindDirection type="風向" unit="８方位漢字" description="南の風">南</jmx_eb:WindDirection>
</Base>
</WindDirectionPart>
<WindSpeedPart>
<Base>
<Local>
<AreaName>海上</AreaName>
<jmx_eb:WindSpeed type="最大風速" unit="m/s" description="１５メートル">15</jmx_eb:WindSpeed>
</Local>
</Base>
</WindSpeedPart>
</Property>
</Kind>
<Kind>
<Name>波浪注意報</Name>
<Code>16</Code>
<Status>継続</Status>
<Property>
<Type>波</Type>
<AdvisoryPeriod>
<EndTime>
<Date>２５日</Date>
<Term>夕方</Term>
</EndTime>
</AdvisoryPeriod>
<WaveHeightPart>
<Base>
<jmx_eb:WaveHeight type="波高" unit="m" description="２．５メートル">2.5</jmx_eb:WaveHeight>
</Base>
</WaveHeightPart>
</Property>
</Kind>
<Area>
<Name>岡垣町</Name>
<Code>4038300</Code>
</Area>
<ChangeStatus>警報・注意報種別に変化有</ChangeStatus>
</Item>
<Item>
<Kind>
<Name>大雨警報</Name>
<Code>03</Code>
<Status>発表</Status>
<Condition>土砂災害、浸水害</Condition>
<Attention>
<Note>土砂災害警戒</Note>
<Note>浸水警戒</Note>
</Attention>
<Property>
<Type>土砂災害</Type>
<WarningPeriod>
<EndTime>
<Date>２５日</Date>
<Term>昼前</Term>
</EndTime>
</WarningPeriod>
<AdvisoryPeriod>
<EndTime>
<Date>２５日</Date>
<Term>夕方</Term>
</EndTime>
</AdvisoryPeriod>
</Property>
<Property>
<Type>浸水</Type>
<WarningPeriod>
<EndTime>
<Date>２４日</Date>
<Term>夜遅く</Term>
</EndTime>
</WarningPeriod>
<AdvisoryPeriod>
<EndTime>
<Date>２５日</Date>
<Term>朝</Term>
</EndTime>
</AdvisoryPeriod>
<PrecipitationPart>
<Base>
<jmx_eb:Precipitation type="１時間最大雨量" unit="mm" description="８０ミリ">80</jmx_eb:Precipitation>
</Base>
</PrecipitationPart>
</Property>
</Kind>
<Kind>
<Name>洪水警報</Name>
<Code>04</Code>
<Status>発表</Status>
<Addition>
<Note>氾濫</Note>
</Addition>
<Property>
<Type>洪水</Type>
<WarningPeriod>
<EndTime>
<Date>２４日</Date>
<Term>夜遅く</Term>
</EndTime>
</WarningPeriod>
<AdvisoryPeriod>
<EndTime>
<Date>２５日</Date>
<Term>朝</Term>
</EndTime>
</AdvisoryPeriod>
</Property>
</Kind>
<Kind>
<Name>雷注意報</Name>
<Code>14</Code>
<Status>継続</Status>
<Addition>
<Note>竜巻</Note>
</Addition>
<Property>
<Type>雷</Type>
<AdvisoryPeriod>
<EndTime>
<Date>２５日</Date>
<Term>夕方</Term>
</EndTime>
</AdvisoryPeriod>
</Property>
</Kind>
<Area>
<Name>遠賀町</Name>
<Code>4038400</Code>
</Area>
<ChangeStatus>警報・注意報種別に変化有</ChangeStatus>
</Item>
<Item>
<Kind>
<Name>雷注意報</Name>
<Code>14</Code>
<Status>継続</Status>
<Addition>
<Note>竜巻</Note>
</Addition>
<Property>
<Type>雷</Type>
<AdvisoryPeriod>
<EndTime>
<Date>２５日</Date>
<Term>夕方</Term>
</EndTime>
</AdvisoryPeriod>
</Property>
</Kind>
<Area>
<Name>小竹町</Name>
<Code>4040100</Code>
</Area>
<ChangeStatus>警報・注意報種別に変化無、量的予想事項等に変化有</ChangeStatus>
</Item>
<Item>
<Kind>
<Name>雷注意報</Name>
<Code>14</Code>
<Status>継続</Status>
<Addition>
<Note>竜巻</Note>
</Addition>
<Property>
<Type>雷</Type>
<AdvisoryPeriod>
<EndTime>
<Date>２５日</Date>
<Term>夕方</Term>
</EndTime>
</AdvisoryPeriod>
</Property>
</Kind>
<Area>
<Name>鞍手町</Name>
<Code>4040200</Code>
</Area>
<ChangeStatus>警報・注意報種別に変化無、量的予想事項等に変化有</ChangeStatus>
</Item>
<Item>
<Kind>
<Name>雷注意報</Name>
<Code>14</Code>
<Status>継続</Status>
<Addition>
<Note>竜巻</Note>
</Addition>
<Property>
<Type>雷</Type>
<AdvisoryPeriod>
<EndTime>
<Date>２５日</Date>
<Term>夕方</Term>
</EndTime>
</AdvisoryPeriod>
</Property>
</Kind>
<Area>
<Name>桂川町</Name>
<Code>4042100</Code>
</Area>
<ChangeStatus>警報・注意報種別に変化無、量的予想事項等に変化有</ChangeStatus>
</Item>
<Item>
<Kind>
<Name>雷注意報</Name>
<Code>14</Code>
<Status>継続</Status>
<Addition>
<Note>竜巻</Note>
</Addition>
<Property>
<Type>雷</Type>
<AdvisoryPeriod>
<EndTime>
<Date>２５日</Date>
<Term>夕方</Term>
</EndTime>
</AdvisoryPeriod>
</Property>
</Kind>
<Area>
<Name>筑前町</Name>
<Code>4044700</Code>
</Area>
<ChangeStatus>警報・注意報種別に変化無、量的予想事項等に変化有</ChangeStatus>
</Item>
<Item>
<Kind>
<Name>雷注意報</Name>
<Code>14</Code>
<Status>継続</Status>
<Addition>
<Note>竜巻</Note>
</Addition>
<Property>
<Type>雷</Type>
<AdvisoryPeriod>
<EndTime>
<Date>２５日</Date>
<Term>夕方</Term>
</EndTime>
</AdvisoryPeriod>
</Property>
</Kind>
<Area>
<Name>東峰村</Name>
<Code>4044800</Code>
</Area>
<ChangeStatus>警報・注意報種別に変化無、量的予想事項等に変化有</ChangeStatus>
</Item>
<Item>
<Kind>
<Name>雷注意報</Name>
<Code>14</Code>
<Status>継続</Status>
<Addition>
<Note>竜巻</Note>
</Addition>
<Property>
<Type>雷</Type>
<AdvisoryPeriod>
<EndTime>
<Date>２５日</Date>
<Term>夕方</Term>
</EndTime>
</AdvisoryPeriod>
</Property>
</Kind>
<Area>
<Name>大刀洗町</Name>
<Code>4050300</Code>
</Area>
<ChangeStatus>警報・注意報種別に変化無、量的予想事項等に変化有</ChangeStatus>
</Item>
<Item>
<Kind>
<Name>雷注意報</Name>
<Code>14</Code>
<Status>継続</Status>
<Addition>
<Note>竜巻</Note>
</Addition>
<Property>
<Type>雷</Type>
<AdvisoryPeriod>
<EndTime>
<Date>２５日</Date>
<Term>夕方</Term>
</EndTime>
</AdvisoryPeriod>
</Property>
</Kind>
<Area>
<Name>大木町</Name>
<Code>4052200</Code>
</Area>
<ChangeStatus>警報・注意報種別に変化無、量的予想事項等に変化有</ChangeStatus>
</Item>
<Item>
<Kind>
<Name>雷注意報</Name>
<Code>14</Code>
<Status>継続</Status>
<Addition>
<Note>竜巻</Note>
</Addition>
<Property>
<Type>雷</Type>
<AdvisoryPeriod>
<EndTime>
<Date>２５日</Date>
<Term>夕方</Term>
</EndTime>
</AdvisoryPeriod>
</Property>
</Kind>
<Area>
<Name>広川町</Name>
<Code>4054400</Code>
</Area>
<ChangeStatus>警報・注意報種別に変化無、量的予想事項等に変化有</ChangeStatus>
</Item>
<Item>
<Kind>
<Name>雷注意報</Name>
<Code>14</Code>
<Status>継続</Status>
<Addition>
<Note>竜巻</Note>
</Addition>
<Property>
<Type>雷</Type>
<AdvisoryPeriod>
<EndTime>
<Date>２５日</Date>
<Term>夕方</Term>
</EndTime>
</AdvisoryPeriod>
</Property>
</Kind>
<Area>
<Name>香春町</Name>
<Code>4060100</Code>
</Area>
<ChangeStatus>警報・注意報種別に変化無、量的予想事項等に変化有</ChangeStatus>
</Item>
<Item>
<Kind>
<Name>雷注意報</Name>
<Code>14</Code>
<Status>継続</Status>
<Addition>
<Note>竜巻</Note>
</Addition>
<Property>
<Type>雷</Type>
<AdvisoryPeriod>
<EndTime>
<Date>２５日</Date>
<Term>夕方</Term>
</EndTime>
</AdvisoryPeriod>
</Property>
</Kind>
<Area>
<Name>添田町</Name>
<Code>4060200</Code>
</Area>
<ChangeStatus>警報・注意報種別に変化無、量的予想事項等に変化有</ChangeStatus>
</Item>
<Item>
<Kind>
<Name>雷注意報</Name>
<Code>14</Code>
<Status>継続</Status>
<Addition>
<Note>竜巻</Note>
</Addition>
<Property>
<Type>雷</Type>
<AdvisoryPeriod>
<EndTime>
<Date>２５日</Date>
<Term>夕方</Term>
</EndTime>
</AdvisoryPeriod>
</Property>
</Kind>
<Area>
<Name>糸田町</Name>
<Code>4060400</Code>
</Area>
<ChangeStatus>警報・注意報種別に変化無、量的予想事項等に変化有</ChangeStatus>
</Item>
<Item>
<Kind>
<Name>雷注意報</Name>
<Code>14</Code>
<Status>継続</Status>
<Addition>
<Note>竜巻</Note>
</Addition>
<Property>
<Type>雷</Type>
<AdvisoryPeriod>
<EndTime>
<Date>２５日</Date>
<Term>夕方</Term>
</EndTime>
</AdvisoryPeriod>
</Property>
</Kind>
<Area>
<Name>川崎町</Name>
<Code>4060500</Code>
</Area>
<ChangeStatus>警報・注意報種別に変化無、量的予想事項等に変化有</ChangeStatus>
</Item>
<Item>
<Kind>
<Name>雷注意報</Name>
<Code>14</Code>
<Status>継続</Status>
<Addition>
<Note>竜巻</Note>
</Addition>
<Property>
<Type>雷</Type>
<AdvisoryPeriod>
<EndTime>
<Date>２５日</Date>
<Term>夕方</Term>
</EndTime>
</AdvisoryPeriod>
</Property>
</Kind>
<Area>
<Name>大任町</Name>
<Code>4060800</Code>
</Area>
<ChangeStatus>警報・注意報種別に変化無、量的予想事項等に変化有</ChangeStatus>
</Item>
<Item>
<Kind>
<Name>雷注意報</Name>
<Code>14</Code>
<Status>継続</Status>
<Addition>
<Note>竜巻</Note>
</Addition>
<Property>
<Type>雷</Type>
<AdvisoryPeriod>
<EndTime>
<Date>２５日</Date>
<Term>夕方</Term>
</EndTime>
</AdvisoryPeriod>
</Property>
</Kind>
<Area>
<Name>赤村</Name>
<Code>4060900</Code>
</Area>
<ChangeStatus>警報・注意報種別に変化無、量的予想事項等に変化有</ChangeStatus>
</Item>
<Item>
<Kind>
<Name>雷注意報</Name>
<Code>14</Code>
<Status>継続</Status>
<Addition>
<Note>竜巻</Note>
</Addition>
<Property>
<Type>雷</Type>
<AdvisoryPeriod>
<EndTime>
<Date>２５日</Date>
<Term>夕方</Term>
</EndTime>
</AdvisoryPeriod>
</Property>
</Kind>
<Area>
<Name>福智町</Name>
<Code>4061000</Code>
</Area>
<ChangeStatus>警報・注意報種別に変化無、量的予想事項等に変化有</ChangeStatus>
</Item>
<Item>
<Kind>
<Name>雷注意報</Name>
<Code>14</Code>
<Status>継続</Status>
<Addition>
<Note>竜巻</Note>
</Addition>
<Property>
<Type>雷</Type>
<AdvisoryPeriod>
<EndTime>
<Date>２５日</Date>
<Term>夕方</Term>
</EndTime>
</AdvisoryPeriod>
</Property>
</Kind>
<Kind>
<Name>強風注意報</Name>
<Code>15</Code>
<Status>継続</Status>
<Property>
<Type>風</Type>
<AdvisoryPeriod>
<EndTime>
<Date>２４日</Date>
<Term>夜のはじめ頃</Term>
</EndTime>
</AdvisoryPeriod>
<WindDirectionPart>
<Base>
<jmx_eb:WindDirection type="風向" unit="８方位漢字" description="南東の風">南東</jmx_eb:WindDirection>
</Base>
</WindDirectionPart>
<WindSpeedPart>
<Base>
<Local>
<AreaName>海上</AreaName>
<jmx_eb:WindSpeed type="最大風速" unit="m/s" description="１２メートル">12</jmx_eb:WindSpeed>
</Local>
</Base>
</WindSpeedPart>
</Property>
</Kind>
<Area>
<Name>苅田町</Name>
<Code>4062100</Code>
</Area>
<ChangeStatus>警報・注意報種別に変化無、量的予想事項等に変化有</ChangeStatus>
</Item>
<Item>
<Kind>
<Name>雷注意報</Name>
<Code>14</Code>
<Status>継続</Status>
<Addition>
<Note>竜巻</Note>
</Addition>
<Property>
<Type>雷</Type>
<AdvisoryPeriod>
<EndTime>
<Date>２５日</Date>
<Term>夕方</Term>
</EndTime>
</AdvisoryPeriod>
</Property>
</Kind>
<Area>
<Name>みやこ町</Name>
<Code>4062500</Code>
</Area>
<ChangeStatus>警報・注意報種別に変化無、量的予想事項等に変化有</ChangeStatus>
</Item>
<Item>
<Kind>
<Name>雷注意報</Name>
<Code>14</Code>
<Status>継続</Status>
<Addition>
<Note>竜巻</Note>
</Addition>
<Property>
<Type>雷</Type>
<AdvisoryPeriod>
<EndTime>
<Date>２５日</Date>
<Term>夕方</Term>
</EndTime>
</AdvisoryPeriod>
</Property>
</Kind>
<Kind>
<Name>強風注意報</Name>
<Code>15</Code>
<Status>継続</Status>
<Property>
<Type>風</Type>
<AdvisoryPeriod>
<EndTime>
<Date>２４日</Date>
<Term>夜のはじめ頃</Term>
</EndTime>
</AdvisoryPeriod>
<WindDirectionPart>
<Base>
<jmx_eb:WindDirection type="風向" unit="８方位漢字" description="南東の風">南東</jmx_eb:WindDirection>
</Base>
</WindDirectionPart>
<WindSpeedPart>
<Base>
<Local>
<AreaName>海上</AreaName>
<jmx_eb:WindSpeed type="最大風速" unit="m/s" description="１２メートル">12</jmx_eb:WindSpeed>
</Local>
</Base>
</WindSpeedPart>
</Property>
</Kind>
<Area>
<Name>吉富町</Name>
<Code>4064200</Code>
</Area>
<ChangeStatus>警報・注意報種別に変化無、量的予想事項等に変化有</ChangeStatus>
</Item>
<Item>
<Kind>
<Name>雷注意報</Name>
<Code>14</Code>
<Status>継続</Status>
<Addition>
<Note>竜巻</Note>
</Addition>
<Property>
<Type>雷</Type>
<AdvisoryPeriod>
<EndTime>
<Date>２５日</Date>
<Term>夕方</Term>
</EndTime>
</AdvisoryPeriod>
</Property>
</Kind>
<Area>
<Name>上毛町</Name>
<Code>4064600</Code>
</Area>
<ChangeStatus>警報・注意報種別に変化無、量的予想事項等に変化有</ChangeStatus>
</Item>
<Item>
<Kind>
<Name>雷注意報</Name>
<Code>14</Code>
<Status>継続</Status>
<Addition>
<Note>竜巻</Note>
</Addition>
<Property>
<Type>雷</Type>
<AdvisoryPeriod>
<EndTime>
<Date>２５日</Date>
<Term>夕方</Term>
</EndTime>
</AdvisoryPeriod>
</Property>
</Kind>
<Kind>
<Name>強風注意報</Name>
<Code>15</Code>
<Status>継続</Status>
<Property>
<Type>風</Type>
<AdvisoryPeriod>
<EndTime>
<Date>２４日</Date>
<Term>夜のはじめ頃</Term>
</EndTime>
</AdvisoryPeriod>
<WindDirectionPart>
<Base>
<jmx_eb:WindDirection type="風向" unit="８方位漢字" description="南東の風">南東</jmx_eb:WindDirection>
</Base>
</WindDirectionPart>
<WindSpeedPart>
<Base>
<Local>
<AreaName>海上</AreaName>
<jmx_eb:WindSpeed type="最大風速" unit="m/s" description="１２メートル">12</jmx_eb:WindSpeed>
</Local>
</Base>
</WindSpeedPart>
</Property>
</Kind>
<Area>
<Name>築上町</Name>
<Code>4064700</Code>
</Area>
<ChangeStatus>警報・注意報種別に変化無、量的予想事項等に変化有</ChangeStatus>
</Item>
</Warning>
</Body>
</Report>
