<?xml version="1.0" encoding="utf-8"?>
<Report xmlns="http://xml.kishou.go.jp/jmaxml1/" xmlns:jmx="http://xml.kishou.go.jp/jmaxml1/" xmlns:jmx_add="http://xml.kishou.go.jp/jmaxml1/addition1/">
  <Control>
    <Title>地方気象情報</Title>
    <DateTime>2009-07-24T11:30:10Z</DateTime>
    <Status>通常</Status>
    <EditorialOffice>福岡管区気象台</EditorialOffice>
    <PublishingOffice>福岡管区気象台</PublishingOffice>
  </Control>
  <Head xmlns="http://xml.kishou.go.jp/jmaxml1/informationBasis1/">
    <Title>大雨と突風に関する九州北部地方（山口県を含む）気象情報</Title>
    <ReportDateTime>2009-07-24T20:30:00+09:00</ReportDateTime>
    <TargetDateTime>2009-07-24T20:30:00+09:00</TargetDateTime>
    <EventID>JPFK090052</EventID>
    <InfoType>発表</InfoType>
    <Serial>5</Serial>
    <InfoKind>同一現象用平文情報</InfoKind>
    <InfoKindVersion>1.0_0</InfoKindVersion>
    <Headline>
      <Text>福岡県と佐賀県では１時間１００ミリ以上の猛烈な雨が降りました。九州北部地方では引き続き２５日昼過ぎにかけて大雨となる見込みです。土砂災害や洪水の危険度が高くなっている所があり、厳重な警戒が必要です。</Text>
    </Headline>
  </Head>
  <Body xmlns="http://xml.kishou.go.jp/jmaxml1/body/meteorology1/">
    <Notice/>
    <Comment>
      <Text type="本文">　梅雨前線が対馬海峡に停滞し、活動が活発になっています。
　福岡県と佐賀県では１時間１００ミリ以上の猛烈な雨が降りました。
　九州北部地方では、土砂災害や洪水の危険度が高くなっている所がありま
す。
　梅雨前線は２５日も活動が活発な状態が続き、対馬海峡からゆっくり南下
する見込みです。

　九州北部地方では、２４日夜は局地的に猛烈な雨が降るおそれがあります
。２５日も昼過ぎにかけて非常に激しい雨が降る所がある見込みです。
　また、２５日にかけて落雷や竜巻などの激しい突風のおそれもあります。

＜雨の予想＞
　１時間最大雨量
　　２４日　福岡県　８０ミリ　　
　　　　　　長崎県・佐賀県　７０ミリ
　　　　　　山口県　６０ミリ
　　　　　　大分県・熊本県　４０ミリ
　　２５日　福岡県・長崎県・佐賀県　５０ミリ
　　　　　　山口県・大分県・熊本県　４０ミリ
　　
　２５日２１時までの２４時間雨量（多い所）
　　　福岡県　２５０ミリ
　　　長崎県・佐賀県　２００ミリ
　　　山口県　１５０ミリ
　　　大分県・熊本県　１２０ミリ
　　　　
＜防災事項＞
　山崩れやがけ崩れなどの土砂災害、河川の増水や氾濫、低地の浸水に厳重
に警戒して下さい。
　落雷や竜巻などの激しい突風に注意して下さい。

　地元の気象台が発表する警報や注意報、気象情報に留意して下さい。
　次の「大雨と突風に関する九州北部地方（山口県を含む）気象情報」は、
２４日２３時３０分頃発表の予定です。</Text>
    </Comment>
  </Body>
</Report>
