{
  "control": {
    "title": "気象警報・注意報（Ｈ２７）",
    "dateTime": "2021-09-14T04:42:24Z",
    "status": "通常",
    "editorialOffice": "徳島地方気象台",
    "publishingOffices": [
      "徳島地方気象台"
    ]
  },
  "head": {
    "title": "徳島県気象警報・注意報",
    "reportDateTime": "2021-09-14T04:42:00Z",
    "targetDateTime": "2021-09-14T04:42:00Z",
    "eventID": "",
    "infoType": "発表",
    "serial": "",
    "infoKind": "気象警報・注意報",
    "infoKindVersion": "1.2_2",
    "headline": {
      "text": "北部では、１４日夜のはじめ頃まで高潮に警戒してください。",
      "informations": [
        {
          "type": "気象警報・注意報（府県予報区等）",
          "items": [
            {
              "kinds": [
                {
                  "name": "高潮警報",
                  "code": "08"
                }
              ],
              "areas": {
                "codeType": "気象情報／府県予報区・細分区域等",
                "areas": [
                  {
                    "name": "徳島県",
                    "code": "360000"
                  }
                ]
              }
            }
          ]
        },
        {
          "type": "気象警報・注意報（一次細分区域等）",
          "items": [
            {
              "kinds": [
                {
                  "name": "高潮警報",
                  "code": "08"
                }
              ],
              "areas": {
                "codeType": "気象情報／府県予報区・細分区域等",
                "areas": [
                  {
                    "name": "北部",
                    "code": "360010"
                  }
                ]
              }
            }
          ]
        },
        {
          "type": "気象警報・注意報（市町村等をまとめた地域等）",
          "items": [
            {
              "kinds": [
                {
                  "name": "高潮警報",
                  "code": "08"
                }
              ],
              "areas": {
                "codeType": "気象情報／府県予報区・細分区域等",
                "areas": [
                  {
                    "name": "徳島・鳴門",
                    "code": "360011"
                  }
                ]
              }
            }
          ]
        },
        {
          "type": "気象警報・注意報（市町村等）",
          "items": [
            {
              "kinds": [
                {
                  "name": "高潮警報",
                  "code": "08"
                }
              ],
              "areas": {
                "codeType": "気象・地震・火山情報／市町村等",
                "areas": [
                  {
                    "name": "藍住町",
                    "code": "3640300"
                  }
                ]
              }
            }
          ]
        },
        {
          "type": "気象警報・注意報（警報注意報種別毎）",
          "items": [
            {
              "kinds": [
                {
                  "name": "高潮警報",
                  "code": "08"
                }
              ],
              "areas": {
                "codeType": "気象情報／府県予報区・細分区域等",
                "areas": [
                  {
                    "name": "徳島・鳴門",
                    "code": "360011"
                  }
                ]
              }
            }
          ]
        }
      ]
    }
  },
  "meteBody": {
    "warnings": [
      {
        "type": "気象警報・注意報（府県予報区等）",
        "items": [
          {
            "kinds": [
              {
                "name": "高潮警報",
                "code": "08",
                "status": "発表"
              }
            ],
            "area": {
              "name": "徳島県",
              "code": "360000"
            },
            "changeStatus": "警報・注意報種別に変化有",
            "fullStatus": "一部",
            "editingMark": "0"
          }
        ]
      },
      {
        "type": "気象警報・注意報（一次細分区域等）",
        "items": [
          {
            "kinds": [
              {
                "name": "高潮警報",
                "code": "08",
                "status": "発表"
              }
            ],
            "area": {
              "name": "北部",
              "code": "360010"
            },
            "changeStatus": "警報・注意報種別に変化有",
            "fullStatus": "一部",
            "editingMark": "0"
          },
          {
            "kinds": [
              {
                "status": "発表警報・注意報はなし"
              }
            ],
            "area": {
              "name": "南部",
              "code": "360020"
            }
          }
        ]
      },
      {
        "type": "気象警報・注意報（市町村等をまとめた地域等）",
        "items": [
          {
            "kinds": [
              {
                "name": "高潮警報",
                "code": "08",
                "status": "発表"
              }
            ],
            "area": {
              "name": "徳島・鳴門",
              "code": "360011"
            },
            "changeStatus": "警報・注意報種別に変化有",
            "fullStatus": "一部",
            "editingMark": "1"
          },
          {
            "kinds": [
              {
                "status": "発表警報・注意報はなし"
              }
            ],
            "area": {
              "name": "美馬北部・阿北",
              "code": "360012"
            }
          },
          {
            "kinds": [
              {
                "status": "発表警報・注意報はなし"
              }
            ],
            "area": {
              "name": "美馬南部・神山",
              "code": "360013"
            }
          },
          {
            "kinds": [
              {
                "status": "発表警報・注意報はなし"
              }
            ],
            "area": {
              "name": "三好",
              "code": "360014"
            }
          },
          {
            "kinds": [
              {
                "status": "発表警報・注意報はなし"
              }
            ],
            "area": {
              "name": "阿南",
              "code": "360021"
            }
          },
          {
            "kinds": [
              {
                "status": "発表警報・注意報はなし"
              }
            ],
            "area": {
              "name": "那賀・勝浦",
              "code": "360022"
            }
          },
          {
            "kinds": [
              {
                "status": "発表警報・注意報はなし"
              }
            ],
            "area": {
              "name": "海部",
              "code": "360023"
            }
          }
        ]
      },
      {
        "type": "気象警報・注意報（市町村等）",
        "items": [
          {
            "kinds": [
              {
                "status": "発表警報・注意報はなし"
              }
            ],
            "area": {
              "name": "徳島市",
              "code": "3620100"
            }
          },
          {
            "kinds": [
              {
                "status": "発表警報・注意報はなし"
              }
            ],
            "area": {
              "name": "鳴門市",
              "code": "3620200"
            }
          },
          {
            "kinds": [
              {
                "status": "発表警報・注意報はなし"
              }
            ],
            "area": {
              "name": "小松島市",
              "code": "3620300"
            }
          },
          {
            "kinds": [
              {
                "status": "発表警報・注意報はなし"
              }
            ],
            "area": {
              "name": "阿南市",
              "code": "3620400"
            }
          },
          {
            "kinds": [
              {
                "status": "発表警報・注意報はなし"
              }
            ],
            "area": {
              "name": "吉野川市",
              "code": "3620500"
            }
          },
          {
            "kinds": [
              {
                "status": "発表警報・注意報はなし"
              }
            ],
            "area": {
              "name": "阿波市",
              "code": "3620600"
            }
          },
          {
            "kinds": [
              {
                "status": "発表警報・注意報はなし"
              }
            ],
            "area": {
              "name": "美馬市脇・美馬・穴吹",
              "code": "3620701"
            }
          },
          {
            "kinds": [
              {
                "status": "発表警報・注意報はなし"
              }
            ],
            "area": {
              "name": "美馬市木屋平",
              "code": "3620702"
            }
          },
          {
            "kinds": [
              {
                "status": "発表警報・注意報はなし"
              }
            ],
            "area": {
              "name": "三好市",
              "code": "3620800"
            }
          },
          {
            "kinds": [
              {
                "status": "発表警報・注意報はなし"
              }
            ],
            "area": {
              "name": "勝浦町",
              "code": "3630100"
            }
          },
          {
            "kinds": [
              {
                "status": "発表警報・注意報はなし"
              }
            ],
            "area": {
              "name": "上勝町",
              "code": "3630200"
            }
          },
          {
            "kinds": [
              {
                "status": "発表警報・注意報はなし"
              }
            ],
            "area": {
              "name": "佐那河内村",
              "code": "3632100"
            }
          },
          {
            "kinds": [
              {
                "status": "発表警報・注意報はなし"
              }
            ],
            "area": {
              "name": "石井町",
              "code": "3634100"
            }
          },
          {
            "kinds": [
              {
                "status": "発表警報・注意報はなし"
              }
            ],
            "area": {
              "name": "神山町",
              "code": "3634200"
            }
          },
          {
            "kinds": [
              {
                "status": "発表警報・注意報はなし"
              }
            ],
            "area": {
              "name": "那賀町",
              "code": "3636800"
            }
          },
          {
            "kinds": [
              {
                "status": "発表警報・注意報はなし"
              }
            ],
            "area": {
              "name": "牟岐町",
              "code": "3638300"
            }
          },
          {
            "kinds": [
              {
                "status": "発表警報・注意報はなし"
              }
            ],
            "area": {
              "name": "美波町",
              "code": "3638700"
            }
          },
          {
            "kinds": [
              {
                "status": "発表警報・注意報はなし"
              }
            ],
            "area": {
              "name": "海陽町",
              "code": "3638800"
            }
          },
          {
            "kinds": [
              {
                "status": "発表警報・注意報はなし"
              }
            ],
            "area": {
              "name": "松茂町",
              "code": "3640100"
            }
          },
          {
            "kinds": [
              {
                "status": "発表警報・注意報はなし"
              }
            ],
            "area": {
              "name": "北島町",
              "code": "3640200"
            }
          },
          {
            "kinds": [
              {
                "name": "高潮警報",
                "code": "08",
                "status": "発表"
              }
            ],
            "area": {
              "name": "藍住町",
              "code": "3640300"
            },
            "changeStatus": "警報・注意報種別に変化有"
          },
          {
            "kinds": [
              {
                "status": "発表警報・注意報はなし"
              }
            ],
            "area": {
              "name": "板野町",
              "code": "3640400"
            }
          },
          {
            "kinds": [
              {
                "status": "発表警報・注意報はなし"
              }
            ],
            "area": {
              "name": "上板町",
              "code": "3640500"
            }
          },
          {
            "kinds": [
              {
                "status": "発表警報・注意報はなし"
              }
            ],
            "area": {
              "name": "つるぎ町半田・貞光",
              "code": "3646801"
            }
          },
          {
            "kinds": [
              {
                "status": "発表警報・注意報はなし"
              }
            ],
            "area": {
              "name": "つるぎ町一宇",
              "code": "3646802"
            }
          },
          {
            "kinds": [
              {
                "status": "発表警報・注意報はなし"
              }
            ],
            "area": {
              "name": "東みよし町",
              "code": "3648900"
            }
          }
        ]
      }
    ],
    "meteorologicalInfos": [
      {
        "type": "量的予想時系列（市町村等）",
        "timeSeriesInfos": [
          {
            "timeDefines": {
              "timeDefines": [
                {
                  "timeId": 1,
                  "dateTime": {
                    "value": "2021-09-14T03:00:00Z"
                  },
                  "duration": "PT3H",
                  "name": "１４日昼過ぎ"
                },
                {
                  "timeId": 2,
                  "dateTime": {
                    "value": "2021-09-14T06:00:00Z"
                  },
                  "duration": "PT3H",
                  "name": "１４日夕方"
                },
                {
                  "timeId": 3,
                  "dateTime": {
                    "value": "2021-09-14T09:00:00Z"
                  },
                  "duration": "PT3H",
                  "name": "１４日夜のはじめ頃"
                },
                {
                  "timeId": 4,
                  "dateTime": {
                    "value": "2021-09-14T12:00:00Z"
                  },
                  "duration": "PT3H",
                  "name": "１４日夜遅く"
                },
                {
                  "timeId": 5,
                  "dateTime": {
                    "value": "2021-09-14T15:00:00Z"
                  },
                  "duration": "PT3H",
                  "name": "１５日未明"
                },
                {
                  "timeId": 6,
                  "dateTime": {
                    "value": "2021-09-14T18:00:00Z"
                  },
                  "duration": "PT3H",
                  "name": "１５日明け方"
                },
                {
                  "timeId": 7,
                  "dateTime": {
                    "value": "2021-09-14T21:00:00Z"
                  },
                  "duration": "PT3H",
                  "name": "１５日朝"
                },
                {
                  "timeId": 8,
                  "dateTime": {
                    "value": "2021-09-15T00:00:00Z"
                  },
                  "duration": "PT3H",
                  "name": "１５日昼前"
                },
                {
                  "timeId": 9,
                  "dateTime": {
                    "value": "2021-09-15T03:00:00Z"
                  },
                  "duration": "PT3H",
                  "name": "１５日昼過ぎ"
                }
              ]
            },
            "items": [
              {
                "kinds": [
                  {
                    "name": "高潮警報",
                    "code": "08",
                    "properties": [
                      {
                        "type": "危険度",
                        "significancyParts": [
                          {
                            "base": {
                              "significancies": [
                                {
                                  "type": "高潮危険度",
                                  "refID": 1,
                                  "name": "警報級",
                                  "code": "30"
                                },
                                {
                                  "type": "高潮危険度",
                                  "refID": 2,
                                  "name": "警報級",
                                  "code": "30"
                                },
                                {
                                  "type": "高潮危険度",
                                  "refID": 3,
                                  "name": "警報級",
                                  "code": "30"
                                },
                                {
                                  "type": "高潮危険度",
                                  "refID": 4,
                                  "name": "注意報級未満",
                                  "code": "00"
                                },
                                {
                                  "type": "高潮危険度",
                                  "refID": 5,
                                  "name": "注意報級未満",
                                  "code": "00"
                                },
                                {
                                  "type": "高潮危険度",
                                  "refID": 6,
                                  "name": "注意報級未満",
                                  "code": "00"
                                },
                                {
                                  "type": "高潮危険度",
                                  "refID": 7,
                                  "name": "注意報級未満",
                                  "code": "00"
                                },
                                {
                                  "type": "高潮危険度",
                                  "refID": 8,
                                  "name": "注意報級未満",
                                  "code": "00"
                                },
                                {
                                  "type": "高潮危険度",
                                  "refID": 9,
                                  "name": "注意報級未満",
                                  "code": "00"
                                }
                              ]
                            }
                          }
                        ]
                      },
                      {
                        "type": "高潮",
                        "tidalLevelPart": {
                          "base": {
                            "tidalLevels": [
                              {
                                "value": null,
                                "type": "最高潮位",
                                "unit": "m",
                                "refID": 1,
                                "condition": "値なし"
                              },
                              {
                                "value": null,
                                "type": "最高潮位",
                                "unit": "m",
                                "refID": 2,
                                "condition": "値なし"
                              },
                              {
                                "value": null,
                                "type": "最高潮位",
                                "unit": "m",
                                "refID": 3,
                                "condition": "値なし"
                              },
                              {
                                "value": null,
                                "type": "最高潮位",
                                "unit": "m",
                                "refID": 4,
                                "condition": "値なし"
                              },
                              {
                                "value": null,
                                "type": "最高潮位",
                                "unit": "m",
                                "refID": 5,
                                "condition": "値なし"
                              },
                              {
                                "value": null,
                                "type": "最高潮位",
                                "unit": "m",
                                "refID": 6,
                                "condition": "値なし"
                              },
                              {
                                "value": null,
                                "type": "最高潮位",
                                "unit": "m",
                                "refID": 7,
                                "condition": "値なし"
                              },
                              {
                                "value": null,
                                "type": "最高潮位",
                                "unit": "m",
                                "refID": 8,
                                "condition": "値なし"
                              },
                              {
                                "value": null,
                                "type": "最高潮位",
                                "unit": "m",
                                "refID": 9,
                                "condition": "値なし"
                              }
                            ]
                          }
                        }
                      }
                    ]
                  }
                ],
                "area": {
                  "name": "藍住町",
                  "code": "3640300"
                }
              }
            ]
          }
        ]
      }
    ]
  }
}