{
  "control": {
    "title": "地方気象解説情報（潮位）",
    "dateTime": "2025-04-25T02:05:14Z",
    "status": "通常",
    "editorialOffice": "福岡管区気象台",
    "publishingOffices": [
      "福岡管区気象台"
    ]
  },
  "head": {
    "title": "九州北部地方（山口県含む）気象解説情報（大潮）",
    "reportDateTime": "2025-04-25T02:05:00Z",
    "targetDateTime": "2025-04-25T02:05:00Z",
    "eventID": "JPFK250034",
    "infoType": "発表",
    "serial": "7",
    "infoKind": "気象解説情報",
    "infoKindVersion": "1.5_0",
    "headline": {
      "text": "４月２８日の新月の前後は大潮の時期にあたり、満潮の時間帯を中心に潮位が高くなります。九州北部地方（山口県を含む）の一部の沿岸では、海岸や河口付近の低い土地で浸水や冠水のおそれがあります。",
      "informations": [
        {
          "type": "情報タグ",
          "items": [
            {
              "kinds": [
                {
                  "name": "情報タグ",
                  "condition": "大潮"
                }
              ],
              "areas": {
                "codeType": "全国・地方予報区等",
                "areas": [
                  {
                    "name": "九州北部地方（山口県を含む）",
                    "code": "010900"
                  }
                ]
              }
            }
          ]
        }
      ]
    }
  },
  "body": {
    "type": "meteorology",
    "meteorologicalInfos": [
      {
        "type": "概況",
        "meteorologicalInfos": [
          {
            "dateTime": {
              "value": "2025-04-25T02:05:00Z"
            },
            "items": [
              {
                "kinds": [
                  {
                    "properties": [
                      {
                        "type": "気象概況",
                        "texts": [
                          {
                            "value": "　４月２８日の新月の前後は大潮の時期にあたるため、満潮の時間帯を中心に潮位が高くなります。",
                            "type": "本文"
                          }
                        ]
                      }
                    ]
                  }
                ]
              }
            ]
          }
        ]
      },
      {
        "type": "防災事項",
        "meteorologicalInfos": [
          {
            "dateTime": {
              "value": "2025-04-25T02:05:00Z"
            },
            "items": [
              {
                "kinds": [
                  {
                    "properties": [
                      {
                        "type": "防災事項",
                        "texts": [
                          {
                            "value": "　長崎県、熊本県の一部の沿岸では、４月２６日から４月２９日にかけて、満潮の時間帯を中心に海岸や河口付近の低い土地で浸水や冠水のおそれがありますので注意してください。\n　また、この期間中に低気圧が接近・通過した場合や、海面が短時間に昇降を繰り返す副振動の発生等があった場合には、さらに潮位が上昇する可能性があります。",
                            "type": "本文"
                          }
                        ]
                      }
                    ]
                  }
                ]
              }
            ]
          }
        ]
      },
      {
        "type": "付加情報",
        "meteorologicalInfos": [
          {
            "dateTime": {
              "value": "2025-04-25T02:05:00Z"
            },
            "items": [
              {
                "kinds": [
                  {
                    "properties": [
                      {
                        "type": "補足事項",
                        "texts": [
                          {
                            "value": "今後発表される高潮警報・注意報や気象解説情報に十分留意してください。",
                            "type": "本文"
                          }
                        ]
                      }
                    ]
                  }
                ]
              }
            ]
          }
        ]
      }
    ]
  }
}